[
  {
    "account": "菇菇",
    "title": "空气炸锅 x 地中海吃法！真的香疯了！！！",
    "publishDate": "2026-06-10",
    "exposure": 2,
    "views": 608,
    "ctr": 0.0,
    "likes": 26,
    "comments": 0,
    "saves": 40,
    "followers": 0,
    "shares": 5,
    "avgDuration": 0.0,
    "genre": "图文"
  },
  {
    "account": "18",
    "title": "谁懂啊，菌菇一加，减脂健身餐突然能坚持了",
    "publishDate": "2026-06-10",
    "exposure": 0,
    "views": 36,
    "ctr": 0.0,
    "likes": 0,
    "comments": 0,
    "saves": 1,
    "followers": 0,
    "shares": 0,
    "avgDuration": 0.0,
    "genre": "图文"
  },
  {
    "account": "黄师傅",
    "title": "12种常见可食用野生菌图鉴🍄云南人都爱",
    "publishDate": "2026-06-09",
    "exposure": 1284,
    "views": 199,
    "ctr": 0.121,
    "likes": 11,
    "comments": 5,
    "saves": 2,
    "followers": 0,
    "shares": 0,
    "avgDuration": 25.0,
    "genre": "图文"
  },
  {
    "account": "18",
    "title": "吃得干静真的会瘦！！连吃半个月疯狂掉称！",
    "publishDate": "2026-06-09",
    "exposure": 1379,
    "views": 196,
    "ctr": 0.134,
    "likes": 8,
    "comments": 0,
    "saves": 3,
    "followers": 0,
    "shares": 1,
    "avgDuration": 9.0,
    "genre": "图文"
  },
  {
    "account": "菇菇",
    "title": "连干四碗米饭的懒人焖饭！！！！",
    "publishDate": "2026-06-09",
    "exposure": 2451,
    "views": 165,
    "ctr": 0.064,
    "likes": 15,
    "comments": 0,
    "saves": 12,
    "followers": 0,
    "shares": 0,
    "avgDuration": 14.0,
    "genre": "图文"
  },
  {
    "account": "18",
    "title": "吃得干净真的会瘦！晚餐喝了一周瘦了七斤！",
    "publishDate": "2026-06-08",
    "exposure": 2027,
    "views": 196,
    "ctr": 0.091,
    "likes": 2,
    "comments": 2,
    "saves": 1,
    "followers": 0,
    "shares": 1,
    "avgDuration": 11.0,
    "genre": "图文"
  },
  {
    "account": "菇菇",
    "title": "拌饭~拌饭~拌饭~复刻成功了的香香的拌饭~",
    "publishDate": "2026-06-08",
    "exposure": 1092,
    "views": 188,
    "ctr": 0.161,
    "likes": 4,
    "comments": 0,
    "saves": 3,
    "followers": 0,
    "shares": 3,
    "avgDuration": 7.0,
    "genre": "图文"
  },
  {
    "account": "黄师傅",
    "title": "富公来的喔，商家太大气了，买菌子送牙签喔",
    "publishDate": "2026-06-08",
    "exposure": 924,
    "views": 169,
    "ctr": 0.17,
    "likes": 1,
    "comments": 0,
    "saves": 0,
    "followers": 0,
    "shares": 0,
    "avgDuration": 15.0,
    "genre": "图文"
  },
  {
    "account": "菇菇",
    "title": "解锁羊肚菌：8️⃣道家常菜鲜到舔碗",
    "publishDate": "2026-06-07",
    "exposure": 1999,
    "views": 176,
    "ctr": 0.078,
    "likes": 5,
    "comments": 0,
    "saves": 5,
    "followers": 1,
    "shares": 4,
    "avgDuration": 44.0,
    "genre": "图文"
  },
  {
    "account": "黄师傅",
    "title": "荔枝菌最贵的不是菌，是当天这一口鲜",
    "publishDate": "2026-06-07",
    "exposure": 324,
    "views": 31,
    "ctr": 0.083,
    "likes": 0,
    "comments": 0,
    "saves": 0,
    "followers": 0,
    "shares": 1,
    "avgDuration": 19.0,
    "genre": "图文"
  },
  {
    "account": "黄师傅",
    "title": "为什么荔枝菌一天内就会卖空？",
    "publishDate": "2026-06-07",
    "exposure": 421,
    "views": 29,
    "ctr": 0.069,
    "likes": 0,
    "comments": 0,
    "saves": 0,
    "followers": 0,
    "shares": 0,
    "avgDuration": 6.0,
    "genre": "图文"
  },
  {
    "account": "菇菇",
    "title": "荔枝菌另外4种神仙吃法！鲜味继续升级",
    "publishDate": "2026-06-06",
    "exposure": 3635,
    "views": 135,
    "ctr": 0.036,
    "likes": 3,
    "comments": 0,
    "saves": 2,
    "followers": 0,
    "shares": 0,
    "avgDuration": 25.0,
    "genre": "图文"
  },
  {
    "account": "黄师傅",
    "title": "鸡枞菌、荔枝菌、夏至菇，是不是一种东西？",
    "publishDate": "2026-06-06",
    "exposure": 945,
    "views": 113,
    "ctr": 0.105,
    "likes": 0,
    "comments": 2,
    "saves": 1,
    "followers": 0,
    "shares": 0,
    "avgDuration": 20.0,
    "genre": "图文"
  },
  {
    "account": "菇菇",
    "title": "🔥8种辣椒拼盘，你吃过几种？",
    "publishDate": "2026-06-06",
    "exposure": 1147,
    "views": 69,
    "ctr": 0.058,
    "likes": 1,
    "comments": 0,
    "saves": 0,
    "followers": 1,
    "shares": 0,
    "avgDuration": 9.0,
    "genre": "图文"
  },
  {
    "account": "黄师傅",
    "title": "看懂这几点，就知道荔枝菌为什么价格波动大",
    "publishDate": "2026-06-06",
    "exposure": 405,
    "views": 27,
    "ctr": 0.062,
    "likes": 1,
    "comments": 0,
    "saves": 0,
    "followers": 0,
    "shares": 0,
    "avgDuration": 21.0,
    "genre": "图文"
  },
  {
    "account": "18",
    "title": "夏天一定要试试！荔枝菌和丝瓜太配了",
    "publishDate": "2026-06-06",
    "exposure": 965,
    "views": 26,
    "ctr": 0.024,
    "likes": 0,
    "comments": 0,
    "saves": 3,
    "followers": 0,
    "shares": 0,
    "avgDuration": 9.0,
    "genre": "图文"
  },
  {
    "account": "黄师傅",
    "title": "收藏！黄师傅四招辨别野生羊肚菌",
    "publishDate": "2026-06-05",
    "exposure": 481,
    "views": 43,
    "ctr": 0.085,
    "likes": 0,
    "comments": 0,
    "saves": 1,
    "followers": 0,
    "shares": 0,
    "avgDuration": 16.0,
    "genre": "图文"
  },
  {
    "account": "18",
    "title": "夏天减脂餐天花板！香辣脆嫩超满足",
    "publishDate": "2026-06-05",
    "exposure": 1308,
    "views": 43,
    "ctr": 0.032,
    "likes": 1,
    "comments": 0,
    "saves": 0,
    "followers": 0,
    "shares": 0,
    "avgDuration": 10.0,
    "genre": "图文"
  },
  {
    "account": "黄师傅",
    "title": "疑似荔枝菌？先别急吃！",
    "publishDate": "2026-06-05",
    "exposure": 493,
    "views": 40,
    "ctr": 0.081,
    "likes": 0,
    "comments": 0,
    "saves": 0,
    "followers": 0,
    "shares": 0,
    "avgDuration": 12.0,
    "genre": "图文"
  },
  {
    "account": "黄师傅",
    "title": "一斤两三百的荔枝菌，别毁在清洗这一步",
    "publishDate": "2026-06-05",
    "exposure": 319,
    "views": 22,
    "ctr": 0.069,
    "likes": 0,
    "comments": 0,
    "saves": 0,
    "followers": 0,
    "shares": 0,
    "avgDuration": 14.0,
    "genre": "图文"
  },
  {
    "account": "菇菇",
    "title": "荔枝菌4种神仙吃法！错过等明年",
    "publishDate": "2026-06-05",
    "exposure": 718,
    "views": 18,
    "ctr": 0.022,
    "likes": 0,
    "comments": 0,
    "saves": 0,
    "followers": 0,
    "shares": 0,
    "avgDuration": 6.0,
    "genre": "图文"
  },
  {
    "account": "黄师傅",
    "title": "荔枝菌不是想长就长，原来还要靠白蚁？",
    "publishDate": "2026-06-04",
    "exposure": 675,
    "views": 31,
    "ctr": 0.043,
    "likes": 2,
    "comments": 0,
    "saves": 0,
    "followers": 0,
    "shares": 0,
    "avgDuration": 17.0,
    "genre": "图文"
  },
  {
    "account": "菇菇",
    "title": "荔枝菌拿来煮粥，真的鲜到一口就安静了",
    "publishDate": "2026-06-04",
    "exposure": 619,
    "views": 14,
    "ctr": 0.021,
    "likes": 0,
    "comments": 0,
    "saves": 0,
    "followers": 0,
    "shares": 1,
    "avgDuration": 13.0,
    "genre": "图文"
  },
  {
    "account": "18",
    "title": "荔枝菌冬瓜虾皮汤，清清爽爽但鲜味很足",
    "publishDate": "2026-06-04",
    "exposure": 361,
    "views": 9,
    "ctr": 0.022,
    "likes": 0,
    "comments": 0,
    "saves": 0,
    "followers": 0,
    "shares": 0,
    "avgDuration": 12.0,
    "genre": "图文"
  },
  {
    "account": "菇菇",
    "title": "这锅鲜到离谱！荔枝菌虾仁豆腐煲太适合夏天",
    "publishDate": "2026-06-03",
    "exposure": 2130,
    "views": 33,
    "ctr": 0.015,
    "likes": 1,
    "comments": 0,
    "saves": 2,
    "followers": 0,
    "shares": 0,
    "avgDuration": 6.0,
    "genre": "图文"
  },
  {
    "account": "18",
    "title": "减脂期也能吃香的！荔枝菌鸡胸肉滑蛋",
    "publishDate": "2026-06-03",
    "exposure": 736,
    "views": 28,
    "ctr": 0.037,
    "likes": 2,
    "comments": 0,
    "saves": 0,
    "followers": 1,
    "shares": 0,
    "avgDuration": 20.0,
    "genre": "图文"
  },
  {
    "account": "黄师傅",
    "title": "荔枝菌最鲜的部位，很多人第一口就吃错了",
    "publishDate": "2026-06-03",
    "exposure": 374,
    "views": 27,
    "ctr": 0.075,
    "likes": 1,
    "comments": 0,
    "saves": 0,
    "followers": 0,
    "shares": 0,
    "avgDuration": 5.0,
    "genre": "图文"
  },
  {
    "account": "菇菇",
    "title": "荔枝菌拌面！10分钟香到不想说话",
    "publishDate": "2026-06-02",
    "exposure": 1460,
    "views": 74,
    "ctr": 0.05,
    "likes": 2,
    "comments": 0,
    "saves": 3,
    "followers": 0,
    "shares": 0,
    "avgDuration": 8.0,
    "genre": "图文"
  },
  {
    "account": "黄师傅",
    "title": "摘对了，荔枝菌才鲜甜脆",
    "publishDate": "2026-06-02",
    "exposure": 524,
    "views": 38,
    "ctr": 0.071,
    "likes": 0,
    "comments": 0,
    "saves": 0,
    "followers": 0,
    "shares": 0,
    "avgDuration": 23.0,
    "genre": "图文"
  },
  {
    "account": "18",
    "title": "荔枝菌炒丝瓜鸡蛋，清爽下饭还不腻",
    "publishDate": "2026-06-02",
    "exposure": 656,
    "views": 22,
    "ctr": 0.028,
    "likes": 0,
    "comments": 0,
    "saves": 0,
    "followers": 0,
    "shares": 1,
    "avgDuration": 7.0,
    "genre": "图文"
  },
  {
    "account": "菇菇",
    "title": "这个馅一口爆鲜！包馄饨包饺子都香",
    "publishDate": "2026-06-01",
    "exposure": 1238,
    "views": 81,
    "ctr": 0.063,
    "likes": 1,
    "comments": 0,
    "saves": 5,
    "followers": 0,
    "shares": 2,
    "avgDuration": 20.0,
    "genre": "图文"
  },
  {
    "account": "黄师傅",
    "title": "一年就这一阵，荔枝菌错过真的要等明年",
    "publishDate": "2026-06-01",
    "exposure": 480,
    "views": 42,
    "ctr": 0.082,
    "likes": 1,
    "comments": 0,
    "saves": 0,
    "followers": 0,
    "shares": 0,
    "avgDuration": 5.0,
    "genre": "图文"
  },
  {
    "account": "18",
    "title": "荔枝菌+丝瓜，这碗汤真的清甜到犯规",
    "publishDate": "2026-06-01",
    "exposure": 502,
    "views": 29,
    "ctr": 0.052,
    "likes": 0,
    "comments": 0,
    "saves": 1,
    "followers": 0,
    "shares": 0,
    "avgDuration": 20.0,
    "genre": "图文"
  },
  {
    "account": "18",
    "title": "这碗荔枝菌虾仁豆腐汤，晚餐喝真的太舒服了",
    "publishDate": "2026-05-31",
    "exposure": 440,
    "views": 21,
    "ctr": 0.041,
    "likes": 1,
    "comments": 0,
    "saves": 1,
    "followers": 0,
    "shares": 1,
    "avgDuration": 4.0,
    "genre": "图文"
  },
  {
    "account": "18",
    "title": "减脂期也能吃很香！荔枝菌蒸鸡胸肉饼",
    "publishDate": "2026-05-30",
    "exposure": 533,
    "views": 33,
    "ctr": 0.06,
    "likes": 3,
    "comments": 0,
    "saves": 3,
    "followers": 1,
    "shares": 0,
    "avgDuration": 42.0,
    "genre": "图文"
  },
  {
    "account": "黄师傅",
    "title": "我的天呐！广州街边怎么会有这么多菌子哦",
    "publishDate": "2026-05-29",
    "exposure": 0,
    "views": 32,
    "ctr": 0.0,
    "likes": 1,
    "comments": 0,
    "saves": 0,
    "followers": 0,
    "shares": 0,
    "avgDuration": 0.0,
    "genre": "图文"
  },
  {
    "account": "18",
    "title": "OMG！没想到广州路边也长野菌🍄",
    "publishDate": "2026-05-29",
    "exposure": 174,
    "views": 25,
    "ctr": 0.144,
    "likes": 0,
    "comments": 0,
    "saves": 0,
    "followers": 0,
    "shares": 0,
    "avgDuration": 5.0,
    "genre": "图文"
  },
  {
    "account": "菇菇",
    "title": "真的假的！怎么华南理工大学也有菌子啊",
    "publishDate": "2026-05-29",
    "exposure": 0,
    "views": 23,
    "ctr": 0.0,
    "likes": 0,
    "comments": 0,
    "saves": 0,
    "followers": 0,
    "shares": 0,
    "avgDuration": 0.0,
    "genre": "图文"
  },
  {
    "account": "18",
    "title": "真的假的？！从化荔枝林疑似发现荔枝菌",
    "publishDate": "2026-05-28",
    "exposure": 392,
    "views": 106,
    "ctr": 0.27,
    "likes": 0,
    "comments": 1,
    "saves": 0,
    "followers": 0,
    "shares": 1,
    "avgDuration": 4.0,
    "genre": "图文"
  },
  {
    "account": "二胎妈",
    "title": "爬白云山又发现好多野蘑菇🍄 一路都有",
    "publishDate": "2026-05-28",
    "exposure": 351,
    "views": 54,
    "ctr": 0.123,
    "likes": 0,
    "comments": 3,
    "saves": 0,
    "followers": 0,
    "shares": 0,
    "avgDuration": 11.0,
    "genre": "图文"
  },
  {
    "account": "黄师傅",
    "title": "OMG!海珠湿地的菌子也太多了吧",
    "publishDate": "2026-05-28",
    "exposure": 140,
    "views": 23,
    "ctr": 0.15,
    "likes": 0,
    "comments": 0,
    "saves": 0,
    "followers": 0,
    "shares": 0,
    "avgDuration": 6.0,
    "genre": "图文"
  },
  {
    "account": "菇菇",
    "title": "蛙趣~！！！十八罗汉山雨后遍地是菌子",
    "publishDate": "2026-05-28",
    "exposure": 96,
    "views": 17,
    "ctr": 0.094,
    "likes": 1,
    "comments": 0,
    "saves": 1,
    "followers": 0,
    "shares": 1,
    "avgDuration": 4.0,
    "genre": "图文"
  },
  {
    "account": "菇菇",
    "title": "荔枝菌一斤几百，这么挑才不白花钱",
    "publishDate": "2026-05-27",
    "exposure": 443,
    "views": 67,
    "ctr": 0.097,
    "likes": 0,
    "comments": 0,
    "saves": 1,
    "followers": 0,
    "shares": 2,
    "avgDuration": 31.0,
    "genre": "图文"
  },
  {
    "account": "18",
    "title": "荔枝菌买到了怎么吃",
    "publishDate": "2026-05-27",
    "exposure": 997,
    "views": 53,
    "ctr": 0.052,
    "likes": 1,
    "comments": 0,
    "saves": 1,
    "followers": 1,
    "shares": 0,
    "avgDuration": 20.0,
    "genre": "图文"
  },
  {
    "account": "黄师傅",
    "title": "懂吃的人，已经开始找荔枝菌了",
    "publishDate": "2026-05-27",
    "exposure": 488,
    "views": 44,
    "ctr": 0.082,
    "likes": 1,
    "comments": 0,
    "saves": 0,
    "followers": 0,
    "shares": 1,
    "avgDuration": 16.0,
    "genre": "图文"
  },
  {
    "account": "18",
    "title": "从化荔枝林，发现野生菌啦",
    "publishDate": "2026-05-27",
    "exposure": 246,
    "views": 41,
    "ctr": 0.124,
    "likes": 0,
    "comments": 2,
    "saves": 0,
    "followers": 0,
    "shares": 0,
    "avgDuration": 11.0,
    "genre": "图文"
  },
  {
    "account": "菇菇",
    "title": "市区公园藏着不少小蘑菇✨",
    "publishDate": "2026-05-27",
    "exposure": 267,
    "views": 41,
    "ctr": 0.134,
    "likes": 0,
    "comments": 0,
    "saves": 0,
    "followers": 0,
    "shares": 0,
    "avgDuration": 3.0,
    "genre": "图文"
  },
  {
    "account": "黄师傅",
    "title": "逛植物园偶遇一堆野菌🍄 到处都是",
    "publishDate": "2026-05-27",
    "exposure": 426,
    "views": 34,
    "ctr": 0.069,
    "likes": 0,
    "comments": 0,
    "saves": 0,
    "followers": 0,
    "shares": 1,
    "avgDuration": 5.0,
    "genre": "图文"
  },
  {
    "account": "二胎妈",
    "title": "不是每一朵荔枝菌都值得带回家",
    "publishDate": "2026-05-27",
    "exposure": 404,
    "views": 22,
    "ctr": 0.054,
    "likes": 0,
    "comments": 0,
    "saves": 0,
    "followers": 0,
    "shares": 0,
    "avgDuration": 13.0,
    "genre": "图文"
  },
  {
    "account": "黄师傅",
    "title": "300元斤的荔枝菌，3招认出真（第2招最管用",
    "publishDate": "2026-05-26",
    "exposure": 750,
    "views": 87,
    "ctr": 0.103,
    "likes": 2,
    "comments": 1,
    "saves": 1,
    "followers": 0,
    "shares": 2,
    "avgDuration": 45.0,
    "genre": "图文"
  },
  {
    "account": "18",
    "title": "吃过荔枝菌才知道鲜 不是味精能调出来的",
    "publishDate": "2026-05-26",
    "exposure": 320,
    "views": 45,
    "ctr": 0.144,
    "likes": 1,
    "comments": 0,
    "saves": 1,
    "followers": 0,
    "shares": 0,
    "avgDuration": 7.0,
    "genre": "图文"
  },
  {
    "account": "二胎妈",
    "title": "今年这口鲜，真的不多",
    "publishDate": "2026-05-26",
    "exposure": 285,
    "views": 42,
    "ctr": 0.144,
    "likes": 0,
    "comments": 0,
    "saves": 0,
    "followers": 0,
    "shares": 0,
    "avgDuration": 5.0,
    "genre": "图文"
  },
  {
    "account": "菇菇",
    "title": "狂吃不胖，我教你⑧招",
    "publishDate": "2026-05-26",
    "exposure": 597,
    "views": 28,
    "ctr": 0.045,
    "likes": 2,
    "comments": 0,
    "saves": 1,
    "followers": 0,
    "shares": 0,
    "avgDuration": 33.0,
    "genre": "图文"
  },
  {
    "account": "18",
    "title": "一年只卖30天的荔枝菌到底凭什么贵",
    "publishDate": "2026-05-25",
    "exposure": 749,
    "views": 81,
    "ctr": 0.104,
    "likes": 1,
    "comments": 0,
    "saves": 0,
    "followers": 0,
    "shares": 2,
    "avgDuration": 17.0,
    "genre": "图文"
  },
  {
    "account": "黄师傅",
    "title": "岭南最矜持的菌王，一年只出现15天",
    "publishDate": "2026-05-25",
    "exposure": 707,
    "views": 65,
    "ctr": 0.078,
    "likes": 0,
    "comments": 0,
    "saves": 1,
    "followers": 0,
    "shares": 3,
    "avgDuration": 58.0,
    "genre": "图文"
  },
  {
    "account": "二胎妈",
    "title": "为什么广州本地荔枝菌的价格差这么多？",
    "publishDate": "2026-05-25",
    "exposure": 713,
    "views": 55,
    "ctr": 0.074,
    "likes": 1,
    "comments": 2,
    "saves": 0,
    "followers": 0,
    "shares": 0,
    "avgDuration": 9.0,
    "genre": "图文"
  },
  {
    "account": "菇菇",
    "title": "一年只吃20天，8道吃法快收藏",
    "publishDate": "2026-05-25",
    "exposure": 604,
    "views": 51,
    "ctr": 0.06,
    "likes": 0,
    "comments": 0,
    "saves": 0,
    "followers": 0,
    "shares": 0,
    "avgDuration": 18.0,
    "genre": "图文"
  },
  {
    "account": "黄师傅",
    "title": "荔枝菌大忌：过水洗（增城人教我这样处理",
    "publishDate": "2026-05-24",
    "exposure": 5319,
    "views": 769,
    "ctr": 0.132,
    "likes": 8,
    "comments": 4,
    "saves": 5,
    "followers": 0,
    "shares": 22,
    "avgDuration": 37.0,
    "genre": "图文"
  },
  {
    "account": "菇菇",
    "title": "狂吃不胖，我教你⑧招",
    "publishDate": "2026-05-24",
    "exposure": 1253,
    "views": 32,
    "ctr": 0.026,
    "likes": 0,
    "comments": 0,
    "saves": 1,
    "followers": 0,
    "shares": 0,
    "avgDuration": 8.0,
    "genre": "图文"
  },
  {
    "account": "18",
    "title": "荔枝菌买到了怎么吃",
    "publishDate": "2026-05-24",
    "exposure": 380,
    "views": 30,
    "ctr": 0.079,
    "likes": 0,
    "comments": 0,
    "saves": 0,
    "followers": 0,
    "shares": 0,
    "avgDuration": 13.0,
    "genre": "图文"
  },
  {
    "account": "黄师傅",
    "title": "300元斤的荔枝菌，3招认出真（第2招最管用",
    "publishDate": "2026-05-23",
    "exposure": 797,
    "views": 87,
    "ctr": 0.106,
    "likes": 0,
    "comments": 0,
    "saves": 0,
    "followers": 0,
    "shares": 3,
    "avgDuration": 36.0,
    "genre": "图文"
  },
  {
    "account": "菇菇",
    "title": "荔枝菌一斤几百，这么挑才不白花钱",
    "publishDate": "2026-05-23",
    "exposure": 831,
    "views": 72,
    "ctr": 0.09,
    "likes": 0,
    "comments": 0,
    "saves": 0,
    "followers": 0,
    "shares": 1,
    "avgDuration": 17.0,
    "genre": "图文"
  },
  {
    "account": "18",
    "title": "吃过荔枝菌才知道鲜 不是味精能调出来的",
    "publishDate": "2026-05-23",
    "exposure": 372,
    "views": 42,
    "ctr": 0.096,
    "likes": 0,
    "comments": 0,
    "saves": 0,
    "followers": 0,
    "shares": 0,
    "avgDuration": 17.0,
    "genre": "图文"
  },
  {
    "account": "二胎妈",
    "title": "广东荔枝菌大爆发！！！出门徒步记得带桶",
    "publishDate": "2026-05-22",
    "exposure": 68347,
    "views": 7811,
    "ctr": 0.111,
    "likes": 76,
    "comments": 48,
    "saves": 10,
    "followers": 3,
    "shares": 57,
    "avgDuration": 16.0,
    "genre": "图文"
  },
  {
    "account": "菇菇",
    "title": "吃响铃卷就是在喝油！试试用竹荪代替！",
    "publishDate": "2026-05-22",
    "exposure": 2032,
    "views": 123,
    "ctr": 0.061,
    "likes": 9,
    "comments": 0,
    "saves": 10,
    "followers": 1,
    "shares": 1,
    "avgDuration": 11.0,
    "genre": "图文"
  },
  {
    "account": "菇菇",
    "title": "一年只吃20天，8道吃法快收藏",
    "publishDate": "2026-05-22",
    "exposure": 947,
    "views": 107,
    "ctr": 0.112,
    "likes": 0,
    "comments": 0,
    "saves": 2,
    "followers": 0,
    "shares": 1,
    "avgDuration": 15.0,
    "genre": "图文"
  },
  {
    "account": "菇菇",
    "title": "雨天就想喝这碗松茸山药鲜汤",
    "publishDate": "2026-05-22",
    "exposure": 1533,
    "views": 87,
    "ctr": 0.055,
    "likes": 6,
    "comments": 0,
    "saves": 3,
    "followers": 0,
    "shares": 1,
    "avgDuration": 10.0,
    "genre": "图文"
  },
  {
    "account": "黄师傅",
    "title": "岭南最矜持的菌王，一年只出现15天",
    "publishDate": "2026-05-22",
    "exposure": 614,
    "views": 48,
    "ctr": 0.077,
    "likes": 0,
    "comments": 0,
    "saves": 2,
    "followers": 1,
    "shares": 1,
    "avgDuration": 47.0,
    "genre": "图文"
  },
  {
    "account": "18",
    "title": "一年只卖30天的荔枝菌到底凭什么贵",
    "publishDate": "2026-05-22",
    "exposure": 307,
    "views": 35,
    "ctr": 0.052,
    "likes": 0,
    "comments": 0,
    "saves": 1,
    "followers": 0,
    "shares": 1,
    "avgDuration": 20.0,
    "genre": "图文"
  },
  {
    "account": "二胎妈",
    "title": "逛白云山和搭子发现了鸡枞菌！！！就在拐口",
    "publishDate": "2026-05-21",
    "exposure": 17197,
    "views": 2949,
    "ctr": 0.169,
    "likes": 36,
    "comments": 20,
    "saves": 10,
    "followers": 2,
    "shares": 54,
    "avgDuration": 13.0,
    "genre": "图文"
  },
  {
    "account": "黄师傅",
    "title": "荔枝菌也有时间表？什么时候最嫩一眼看懂",
    "publishDate": "2026-05-21",
    "exposure": 4421,
    "views": 1099,
    "ctr": 0.235,
    "likes": 9,
    "comments": 0,
    "saves": 6,
    "followers": 2,
    "shares": 9,
    "avgDuration": 11.0,
    "genre": "图文"
  },
  {
    "account": "黄师傅",
    "title": "诡异又迷人的10种“真菌”，看完有点破防",
    "publishDate": "2026-05-21",
    "exposure": 8804,
    "views": 1030,
    "ctr": 0.113,
    "likes": 56,
    "comments": 1,
    "saves": 46,
    "followers": 8,
    "shares": 5,
    "avgDuration": 34.0,
    "genre": "图文"
  },
  {
    "account": "菇菇",
    "title": "最近就爱喝这种清清爽爽的菌菇汤",
    "publishDate": "2026-05-21",
    "exposure": 3186,
    "views": 330,
    "ctr": 0.087,
    "likes": 10,
    "comments": 0,
    "saves": 6,
    "followers": 0,
    "shares": 4,
    "avgDuration": 10.0,
    "genre": "图文"
  },
  {
    "account": "18",
    "title": "低卡菌菇麻辣拌，减脂期也能放心炫",
    "publishDate": "2026-05-21",
    "exposure": 1207,
    "views": 89,
    "ctr": 0.073,
    "likes": 6,
    "comments": 0,
    "saves": 8,
    "followers": 1,
    "shares": 1,
    "avgDuration": 21.0,
    "genre": "图文"
  },
  {
    "account": "18",
    "title": "青柠百香果竹荪虾，夏天没胃口直接锁死",
    "publishDate": "2026-05-21",
    "exposure": 1405,
    "views": 68,
    "ctr": 0.048,
    "likes": 7,
    "comments": 0,
    "saves": 6,
    "followers": 1,
    "shares": 1,
    "avgDuration": 7.0,
    "genre": "图文"
  },
  {
    "account": "菇菇",
    "title": "晚餐想吃轻一点，就喝这6款菌香汤",
    "publishDate": "2026-05-21",
    "exposure": 1535,
    "views": 61,
    "ctr": 0.039,
    "likes": 6,
    "comments": 0,
    "saves": 6,
    "followers": 2,
    "shares": 0,
    "avgDuration": 24.0,
    "genre": "图文"
  },
  {
    "account": "菇菇",
    "title": "满口爆汁的鲜！8道羊肚菌食谱益胃养人",
    "publishDate": "2026-05-20",
    "exposure": 21182,
    "views": 5771,
    "ctr": 0.244,
    "likes": 91,
    "comments": 0,
    "saves": 96,
    "followers": 4,
    "shares": 48,
    "avgDuration": 26.0,
    "genre": "图文"
  },
  {
    "account": "18",
    "title": "今日菜谱|和前男友跪求教程的松茸虾仁",
    "publishDate": "2026-05-20",
    "exposure": 1275,
    "views": 42,
    "ctr": 0.034,
    "likes": 5,
    "comments": 0,
    "saves": 0,
    "followers": 0,
    "shares": 0,
    "avgDuration": 12.0,
    "genre": "图文"
  },
  {
    "account": "黄师傅",
    "title": "谁吧鹿角烤碳化了。。",
    "publishDate": "2026-05-20",
    "exposure": 637,
    "views": 32,
    "ctr": 0.049,
    "likes": 1,
    "comments": 0,
    "saves": 2,
    "followers": 0,
    "shares": 0,
    "avgDuration": 9.0,
    "genre": "图文"
  },
  {
    "account": "菇菇",
    "title": "好吃到肘击老公！我不管了！",
    "publishDate": "2026-05-19",
    "exposure": 3935,
    "views": 339,
    "ctr": 0.081,
    "likes": 15,
    "comments": 0,
    "saves": 22,
    "followers": 2,
    "shares": 6,
    "avgDuration": 21.0,
    "genre": "图文"
  },
  {
    "account": "黄师傅",
    "title": "🌙森林不是滤镜，真实存在的梦幻菌菇",
    "publishDate": "2026-05-19",
    "exposure": 2339,
    "views": 171,
    "ctr": 0.071,
    "likes": 12,
    "comments": 0,
    "saves": 11,
    "followers": 0,
    "shares": 0,
    "avgDuration": 11.0,
    "genre": "图文"
  },
  {
    "account": "黄师傅",
    "title": "🍄毒蘑菇警告！铜绿球盖菇结构图鉴",
    "publishDate": "2026-05-19",
    "exposure": 1907,
    "views": 165,
    "ctr": 0.08,
    "likes": 9,
    "comments": 0,
    "saves": 5,
    "followers": 5,
    "shares": 2,
    "avgDuration": 8.0,
    "genre": "图文"
  },
  {
    "account": "18",
    "title": "掉秤快的秘密！这 8 种食物我天天炫",
    "publishDate": "2026-05-19",
    "exposure": 1106,
    "views": 83,
    "ctr": 0.076,
    "likes": 4,
    "comments": 0,
    "saves": 1,
    "followers": 0,
    "shares": 1,
    "avgDuration": 5.0,
    "genre": "图文"
  },
  {
    "account": "菇菇",
    "title": "🍄松茸最香的吃法！黄油一煎真的绝",
    "publishDate": "2026-05-19",
    "exposure": 1005,
    "views": 67,
    "ctr": 0.066,
    "likes": 1,
    "comments": 0,
    "saves": 3,
    "followers": 0,
    "shares": 1,
    "avgDuration": 28.0,
    "genre": "图文"
  },
  {
    "account": "18",
    "title": "越吃越瘦的快手菜｜低卡高蛋白，做法超简单",
    "publishDate": "2026-05-19",
    "exposure": 538,
    "views": 22,
    "ctr": 0.032,
    "likes": 0,
    "comments": 0,
    "saves": 1,
    "followers": 1,
    "shares": 0,
    "avgDuration": 11.0,
    "genre": "图文"
  },
  {
    "account": "菇菇",
    "title": "把“南方红参”端上桌！5道红菇养颜汤",
    "publishDate": "2026-05-18",
    "exposure": 3842,
    "views": 804,
    "ctr": 0.191,
    "likes": 9,
    "comments": 0,
    "saves": 9,
    "followers": 0,
    "shares": 9,
    "avgDuration": 30.0,
    "genre": "图文"
  },
  {
    "account": "菇菇",
    "title": "低卡高蛋白🍄香菇这样吃真的绝了！",
    "publishDate": "2026-05-18",
    "exposure": 2200,
    "views": 193,
    "ctr": 0.087,
    "likes": 9,
    "comments": 0,
    "saves": 7,
    "followers": 0,
    "shares": 0,
    "avgDuration": 14.0,
    "genre": "图文"
  },
  {
    "account": "菇菇",
    "title": "在家复刻🥣莫氏鸡煲竹荪汤香迷糊",
    "publishDate": "2026-05-18",
    "exposure": 1504,
    "views": 121,
    "ctr": 0.08,
    "likes": 1,
    "comments": 0,
    "saves": 2,
    "followers": 0,
    "shares": 0,
    "avgDuration": 15.0,
    "genre": "图文"
  },
  {
    "account": "黄师傅",
    "title": "👻蘑菇长成“骷髅头”？大自然的恶趣味",
    "publishDate": "2026-05-18",
    "exposure": 815,
    "views": 67,
    "ctr": 0.078,
    "likes": 5,
    "comments": 0,
    "saves": 4,
    "followers": 1,
    "shares": 0,
    "avgDuration": 9.0,
    "genre": "图文"
  },
  {
    "account": "黄师傅",
    "title": "森林里的“阿凡达”！会发光的太梦幻了✨",
    "publishDate": "2026-05-18",
    "exposure": 885,
    "views": 50,
    "ctr": 0.055,
    "likes": 5,
    "comments": 0,
    "saves": 2,
    "followers": 0,
    "shares": 0,
    "avgDuration": 7.0,
    "genre": "图文"
  },
  {
    "account": "黄师傅",
    "title": "😨长得像鹿角其实是菌？",
    "publishDate": "2026-05-18",
    "exposure": 324,
    "views": 26,
    "ctr": 0.081,
    "likes": 0,
    "comments": 0,
    "saves": 1,
    "followers": 1,
    "shares": 0,
    "avgDuration": 9.0,
    "genre": "图文"
  },
  {
    "account": "菇菇",
    "title": "下班治愈时刻🍄鸡油菌8吃法香迷糊",
    "publishDate": "2026-05-17",
    "exposure": 4481,
    "views": 731,
    "ctr": 0.156,
    "likes": 12,
    "comments": 0,
    "saves": 15,
    "followers": 0,
    "shares": 4,
    "avgDuration": 30.0,
    "genre": "图文"
  },
  {
    "account": "菇菇",
    "title": "🍄见手青季来了！8道神仙吃法香迷糊",
    "publishDate": "2026-05-17",
    "exposure": 1317,
    "views": 158,
    "ctr": 0.117,
    "likes": 1,
    "comments": 0,
    "saves": 3,
    "followers": 0,
    "shares": 2,
    "avgDuration": 13.0,
    "genre": "图文"
  },
  {
    "account": "18",
    "title": "五月吃这16种应季蔬菜清单🌱顺时吃更舒服",
    "publishDate": "2026-05-17",
    "exposure": 1951,
    "views": 113,
    "ctr": 0.057,
    "likes": 7,
    "comments": 0,
    "saves": 4,
    "followers": 1,
    "shares": 1,
    "avgDuration": 417.0,
    "genre": "图文"
  },
  {
    "account": "黄师傅",
    "title": "问：这种紫色蘑菇能吃吗？答：不能！有毒！",
    "publishDate": "2026-05-17",
    "exposure": 1104,
    "views": 78,
    "ctr": 0.068,
    "likes": 2,
    "comments": 0,
    "saves": 1,
    "followers": 1,
    "shares": 0,
    "avgDuration": 11.0,
    "genre": "图文"
  },
  {
    "account": "黄师傅",
    "title": "这种“紫霞仙子”蘑菇有毒！越美越危险",
    "publishDate": "2026-05-17",
    "exposure": 846,
    "views": 64,
    "ctr": 0.072,
    "likes": 0,
    "comments": 0,
    "saves": 0,
    "followers": 1,
    "shares": 1,
    "avgDuration": 85.0,
    "genre": "图文"
  },
  {
    "account": "菇菇",
    "title": "青头菌养胃汤🍄夏天滋补喝这碗",
    "publishDate": "2026-05-17",
    "exposure": 711,
    "views": 63,
    "ctr": 0.084,
    "likes": 0,
    "comments": 0,
    "saves": 2,
    "followers": 0,
    "shares": 1,
    "avgDuration": 15.0,
    "genre": "图文"
  },
  {
    "account": "黄师傅",
    "title": "蓝瘦香菇？不！这是“天蓝粉褶菌”",
    "publishDate": "2026-05-17",
    "exposure": 706,
    "views": 50,
    "ctr": 0.069,
    "likes": 2,
    "comments": 0,
    "saves": 2,
    "followers": 1,
    "shares": 0,
    "avgDuration": 31.0,
    "genre": "图文"
  },
  {
    "account": "菇菇",
    "title": "下班10分钟🥣这锅奶香菌菇汤太治愈",
    "publishDate": "2026-05-16",
    "exposure": 2125,
    "views": 230,
    "ctr": 0.099,
    "likes": 4,
    "comments": 0,
    "saves": 3,
    "followers": 0,
    "shares": 2,
    "avgDuration": 29.0,
    "genre": "图文"
  },
  {
    "account": "菇菇",
    "title": "赵露思同款🍄这碗菌菇粥鲜绝了",
    "publishDate": "2026-05-16",
    "exposure": 1685,
    "views": 143,
    "ctr": 0.084,
    "likes": 5,
    "comments": 0,
    "saves": 4,
    "followers": 1,
    "shares": 0,
    "avgDuration": 10.0,
    "genre": "图文"
  },
  {
    "account": "黄师傅",
    "title": "🧠“外星生物”竟是毒蘑菇？5月雨季高发",
    "publishDate": "2026-05-16",
    "exposure": 1358,
    "views": 95,
    "ctr": 0.069,
    "likes": 2,
    "comments": 0,
    "saves": 3,
    "followers": 1,
    "shares": 0,
    "avgDuration": 4.0,
    "genre": "图文"
  },
  {
    "account": "18",
    "title": "抗炎饮食我悟了🥦菌菇碗鲜到离谱",
    "publishDate": "2026-05-16",
    "exposure": 1105,
    "views": 85,
    "ctr": 0.077,
    "likes": 3,
    "comments": 0,
    "saves": 6,
    "followers": 1,
    "shares": 1,
    "avgDuration": 10.0,
    "genre": "图文"
  },
  {
    "account": "菇菇",
    "title": "🧀芝士拉丝暴击！松茸饭香迷糊了",
    "publishDate": "2026-05-16",
    "exposure": 946,
    "views": 73,
    "ctr": 0.074,
    "likes": 10,
    "comments": 0,
    "saves": 9,
    "followers": 2,
    "shares": 1,
    "avgDuration": 14.0,
    "genre": "图文"
  },
  {
    "account": "黄师傅",
    "title": "🤯这蘑菇长得好像“大脑”！但真的不能吃",
    "publishDate": "2026-05-16",
    "exposure": 839,
    "views": 45,
    "ctr": 0.053,
    "likes": 2,
    "comments": 0,
    "saves": 0,
    "followers": 0,
    "shares": 0,
    "avgDuration": 10.0,
    "genre": "图文"
  },
  {
    "account": "黄师傅",
    "title": "🍄路边的“小橙帽”，别碰别摘！",
    "publishDate": "2026-05-16",
    "exposure": 614,
    "views": 41,
    "ctr": 0.067,
    "likes": 1,
    "comments": 0,
    "saves": 1,
    "followers": 0,
    "shares": 0,
    "avgDuration": 66.0,
    "genre": "图文"
  },
  {
    "account": "18",
    "title": "回南天救命汤🍄喝完轻盈干爽太绝了",
    "publishDate": "2026-05-16",
    "exposure": 217,
    "views": 12,
    "ctr": 0.055,
    "likes": 2,
    "comments": 0,
    "saves": 0,
    "followers": 0,
    "shares": 0,
    "avgDuration": 27.0,
    "genre": "图文"
  },
  {
    "account": "18",
    "title": "抗炎晚餐🥣羊肚菌虾仁碗暖胃鲜",
    "publishDate": "2026-05-16",
    "exposure": 362,
    "views": 6,
    "ctr": 0.017,
    "likes": 0,
    "comments": 0,
    "saves": 0,
    "followers": 0,
    "shares": 0,
    "avgDuration": 3.0,
    "genre": "图文"
  },
  {
    "account": "二胎妈",
    "title": "你们的荔枝菌都是怎么吃的？",
    "publishDate": "2026-05-14",
    "exposure": 3655,
    "views": 543,
    "ctr": 0.148,
    "likes": 4,
    "comments": 0,
    "saves": 3,
    "followers": 0,
    "shares": 1,
    "avgDuration": 9.0,
    "genre": "图文"
  },
  {
    "account": "二胎妈",
    "title": "打火锅吃竹荪，会有竹子味吗？",
    "publishDate": "2026-05-14",
    "exposure": 1454,
    "views": 139,
    "ctr": 0.094,
    "likes": 2,
    "comments": 0,
    "saves": 0,
    "followers": 0,
    "shares": 0,
    "avgDuration": 9.0,
    "genre": "图文"
  },
  {
    "account": "二胎妈",
    "title": "起猛了，我家狗再给我炒菜",
    "publishDate": "2026-05-13",
    "exposure": 426,
    "views": 155,
    "ctr": 0.054,
    "likes": 1,
    "comments": 2,
    "saves": 1,
    "followers": 1,
    "shares": 0,
    "avgDuration": 21.0,
    "genre": "视频"
  },
  {
    "account": "二胎妈",
    "title": "原来是电视机啊，我还以为是电视机呢",
    "publishDate": "2026-05-13",
    "exposure": 364,
    "views": 126,
    "ctr": 0.055,
    "likes": 7,
    "comments": 0,
    "saves": 5,
    "followers": 4,
    "shares": 0,
    "avgDuration": 23.0,
    "genre": "视频"
  },
  {
    "account": "菇菇",
    "title": "4大古方“轻膳化”，租屋也能轻松养好气色",
    "publishDate": "2026-05-12",
    "exposure": 1384,
    "views": 143,
    "ctr": 0.105,
    "likes": 8,
    "comments": 0,
    "saves": 14,
    "followers": 6,
    "shares": 1,
    "avgDuration": 11.0,
    "genre": "图文"
  },
  {
    "account": "菇菇",
    "title": "火鸡面神仙吃法！脆嫩香辣爆爽🌶️",
    "publishDate": "2026-05-11",
    "exposure": 2168,
    "views": 185,
    "ctr": 0.084,
    "likes": 2,
    "comments": 5,
    "saves": 3,
    "followers": 1,
    "shares": 3,
    "avgDuration": 10.0,
    "genre": "图文"
  },
  {
    "account": "菇菇",
    "title": "云南味道！酸辣鲜香凉拌青头菌，绝了✨",
    "publishDate": "2026-05-11",
    "exposure": 2449,
    "views": 154,
    "ctr": 0.062,
    "likes": 5,
    "comments": 0,
    "saves": 1,
    "followers": 0,
    "shares": 0,
    "avgDuration": 30.0,
    "genre": "图文"
  },
  {
    "account": "黄师傅",
    "title": "识别森林里的“豹纹”刺客",
    "publishDate": "2026-05-11",
    "exposure": 1338,
    "views": 82,
    "ctr": 0.061,
    "likes": 0,
    "comments": 0,
    "saves": 1,
    "followers": 1,
    "shares": 0,
    "avgDuration": 55.0,
    "genre": "图文"
  },
  {
    "account": "黄师傅",
    "title": "林间灰伞：深度揭秘角鳞灰鹅膏菌",
    "publishDate": "2026-05-11",
    "exposure": 1098,
    "views": 77,
    "ctr": 0.067,
    "likes": 1,
    "comments": 0,
    "saves": 0,
    "followers": 0,
    "shares": 0,
    "avgDuration": 7.0,
    "genre": "图文"
  },
  {
    "account": "菇菇",
    "title": "满屋飘香！这口松茸焖饭我能吃三碗🍚",
    "publishDate": "2026-05-11",
    "exposure": 867,
    "views": 75,
    "ctr": 0.084,
    "likes": 3,
    "comments": 0,
    "saves": 3,
    "followers": 0,
    "shares": 0,
    "avgDuration": 25.0,
    "genre": "图文"
  },
  {
    "account": "黄师傅",
    "title": "自然笔记：深度解析橄榄类脐菇物理结构",
    "publishDate": "2026-05-11",
    "exposure": 1136,
    "views": 67,
    "ctr": 0.058,
    "likes": 2,
    "comments": 0,
    "saves": 2,
    "followers": 1,
    "shares": 0,
    "avgDuration": 5.0,
    "genre": "图文"
  },
  {
    "account": "菇菇",
    "title": "鲜掉眉毛！低脂Q弹竹荪酿虾滑教程🍤",
    "publishDate": "2026-05-10",
    "exposure": 4630,
    "views": 480,
    "ctr": 0.102,
    "likes": 15,
    "comments": 0,
    "saves": 10,
    "followers": 0,
    "shares": 1,
    "avgDuration": 38.0,
    "genre": "图文"
  },
  {
    "account": "菇菇",
    "title": "汤鲜味浓！全家都爱的红菇炖鸡汤教程🍲",
    "publishDate": "2026-05-10",
    "exposure": 3487,
    "views": 424,
    "ctr": 0.119,
    "likes": 5,
    "comments": 0,
    "saves": 5,
    "followers": 0,
    "shares": 3,
    "avgDuration": 34.0,
    "genre": "图文"
  },
  {
    "account": "黄师傅",
    "title": "结构解剖：如何识破斑蘑菇的变色伪装？",
    "publishDate": "2026-05-10",
    "exposure": 2300,
    "views": 163,
    "ctr": 0.067,
    "likes": 2,
    "comments": 2,
    "saves": 2,
    "followers": 1,
    "shares": 0,
    "avgDuration": 17.0,
    "genre": "图文"
  },
  {
    "account": "黄师傅",
    "title": "解析纹缘盔孢伞：为何它是林间的危险分子？",
    "publishDate": "2026-05-10",
    "exposure": 1529,
    "views": 103,
    "ctr": 0.065,
    "likes": 3,
    "comments": 0,
    "saves": 1,
    "followers": 1,
    "shares": 2,
    "avgDuration": 12.0,
    "genre": "图文"
  },
  {
    "account": "黄师傅",
    "title": "走近虎皮小牛肝菌：剖析这种“豹纹”菌子",
    "publishDate": "2026-05-10",
    "exposure": 1780,
    "views": 81,
    "ctr": 0.046,
    "likes": 2,
    "comments": 0,
    "saves": 0,
    "followers": 0,
    "shares": 0,
    "avgDuration": 10.0,
    "genre": "图文"
  },
  {
    "account": "菇菇",
    "title": "云南鲜味！爆炒见手青，好吃到舔盘🍄",
    "publishDate": "2026-05-10",
    "exposure": 1181,
    "views": 31,
    "ctr": 0.026,
    "likes": 0,
    "comments": 0,
    "saves": 0,
    "followers": 0,
    "shares": 0,
    "avgDuration": 11.0,
    "genre": "图文"
  },
  {
    "account": "黄师傅",
    "title": "🧊全网最冷！谁把寒冰菇给“切”了？",
    "publishDate": "2026-05-09",
    "exposure": 2598,
    "views": 290,
    "ctr": 0.111,
    "likes": 12,
    "comments": 3,
    "saves": 2,
    "followers": 3,
    "shares": 1,
    "avgDuration": 3.0,
    "genre": "图文"
  },
  {
    "account": "黄师傅",
    "title": "全网最怂！扒这颗“社恐菇”的内心戏🍄",
    "publishDate": "2026-05-09",
    "exposure": 1793,
    "views": 147,
    "ctr": 0.081,
    "likes": 2,
    "comments": 0,
    "saves": 0,
    "followers": 0,
    "shares": 1,
    "avgDuration": 8.0,
    "genre": "图文"
  },
  {
    "account": "黄师傅",
    "title": "一张图看懂洁小菇：森林里的“紫色迷雾”",
    "publishDate": "2026-05-09",
    "exposure": 2022,
    "views": 129,
    "ctr": 0.063,
    "likes": 6,
    "comments": 0,
    "saves": 2,
    "followers": 2,
    "shares": 0,
    "avgDuration": 43.0,
    "genre": "图文"
  },
  {
    "account": "菇菇",
    "title": "拌面配粥神器！自制油鸡枞教程🥢",
    "publishDate": "2026-05-09",
    "exposure": 1612,
    "views": 111,
    "ctr": 0.071,
    "likes": 2,
    "comments": 0,
    "saves": 0,
    "followers": 0,
    "shares": 1,
    "avgDuration": 19.0,
    "genre": "图文"
  },
  {
    "account": "菇菇",
    "title": "鲜到掉眉毛！鸡油菌炒宣威火腿教程🍳",
    "publishDate": "2026-05-09",
    "exposure": 1484,
    "views": 81,
    "ctr": 0.053,
    "likes": 0,
    "comments": 0,
    "saves": 2,
    "followers": 0,
    "shares": 1,
    "avgDuration": 10.0,
    "genre": "图文"
  },
  {
    "account": "菇菇",
    "title": "小巧素雅的菌子，风干之后才显真名士本色！",
    "publishDate": "2026-05-09",
    "exposure": 568,
    "views": 31,
    "ctr": 0.056,
    "likes": 1,
    "comments": 0,
    "saves": 0,
    "followers": 0,
    "shares": 0,
    "avgDuration": 12.0,
    "genre": "图文"
  },
  {
    "account": "黄师傅",
    "title": "救命！路边偶遇黑蘑菇怎么办？在线等急🧨",
    "publishDate": "2026-05-08",
    "exposure": 7566,
    "views": 1165,
    "ctr": 0.156,
    "likes": 21,
    "comments": 3,
    "saves": 7,
    "followers": 5,
    "shares": 3,
    "avgDuration": 6.0,
    "genre": "图文"
  },
  {
    "account": "菇菇",
    "title": "这一口醇厚菌香，是汪曾祺心底的山野清气。",
    "publishDate": "2026-05-08",
    "exposure": 1670,
    "views": 112,
    "ctr": 0.067,
    "likes": 2,
    "comments": 0,
    "saves": 2,
    "followers": 0,
    "shares": 0,
    "avgDuration": 4.0,
    "genre": "图文"
  },
  {
    "account": "黄师傅",
    "title": "🥑抹茶色的诱惑？自带“粉红丝袜”",
    "publishDate": "2026-05-08",
    "exposure": 1548,
    "views": 90,
    "ctr": 0.058,
    "likes": 4,
    "comments": 0,
    "saves": 1,
    "followers": 1,
    "shares": 0,
    "avgDuration": 395.0,
    "genre": "图文"
  },
  {
    "account": "黄师傅",
    "title": "💡避坑指南：长得像柠檬，闻着像“煤气”",
    "publishDate": "2026-05-08",
    "exposure": 1151,
    "views": 80,
    "ctr": 0.069,
    "likes": 1,
    "comments": 0,
    "saves": 0,
    "followers": 0,
    "shares": 0,
    "avgDuration": 228.0,
    "genre": "图文"
  },
  {
    "account": "菇菇",
    "title": "这朵深山里的“丑”菌子，竟藏着极致鲜味！",
    "publishDate": "2026-05-08",
    "exposure": 875,
    "views": 55,
    "ctr": 0.061,
    "likes": 1,
    "comments": 0,
    "saves": 2,
    "followers": 0,
    "shares": 0,
    "avgDuration": 50.0,
    "genre": "图文"
  },
  {
    "account": "18",
    "title": "100期图解蘑菇之阳光菇图鉴",
    "publishDate": "2026-05-08",
    "exposure": 414,
    "views": 32,
    "ctr": 0.073,
    "likes": 0,
    "comments": 0,
    "saves": 0,
    "followers": 0,
    "shares": 0,
    "avgDuration": 5.0,
    "genre": "图文"
  },
  {
    "account": "菇菇",
    "title": "寻味鸡枞，这一口鲜甜是雨季的馈赠！",
    "publishDate": "2026-05-08",
    "exposure": 595,
    "views": 23,
    "ctr": 0.039,
    "likes": 0,
    "comments": 0,
    "saves": 1,
    "followers": 0,
    "shares": 0,
    "avgDuration": 47.0,
    "genre": "图文"
  },
  {
    "account": "黄师傅",
    "title": "🖤自溶的墨汁鬼伞：酒鬼们的“克星”！",
    "publishDate": "2026-05-07",
    "exposure": 5209,
    "views": 795,
    "ctr": 0.15,
    "likes": 28,
    "comments": 3,
    "saves": 7,
    "followers": 1,
    "shares": 3,
    "avgDuration": 17.0,
    "genre": "图文"
  },
  {
    "account": "黄师傅",
    "title": "💡一张图看懂红鬼笔：林地里的“臭气弹”",
    "publishDate": "2026-05-07",
    "exposure": 3725,
    "views": 539,
    "ctr": 0.138,
    "likes": 15,
    "comments": 3,
    "saves": 11,
    "followers": 2,
    "shares": 2,
    "avgDuration": 15.0,
    "genre": "图文"
  },
  {
    "account": "菇菇",
    "title": "跟着汪曾祺云吃牛肝菌，这口鲜香太上头！",
    "publishDate": "2026-05-07",
    "exposure": 2133,
    "views": 144,
    "ctr": 0.067,
    "likes": 0,
    "comments": 0,
    "saves": 6,
    "followers": 1,
    "shares": 0,
    "avgDuration": 8.0,
    "genre": "图文"
  },
  {
    "account": "黄师傅",
    "title": "💡一张图看懂青头菌：森林里的翡翠精灵",
    "publishDate": "2026-05-07",
    "exposure": 2388,
    "views": 141,
    "ctr": 0.059,
    "likes": 6,
    "comments": 0,
    "saves": 1,
    "followers": 1,
    "shares": 0,
    "avgDuration": 23.0,
    "genre": "图文"
  },
  {
    "account": "菇菇",
    "title": "跟着汪曾祺云吃青头菌，这口清雅极致了！",
    "publishDate": "2026-05-07",
    "exposure": 778,
    "views": 60,
    "ctr": 0.076,
    "likes": 3,
    "comments": 0,
    "saves": 0,
    "followers": 0,
    "shares": 0,
    "avgDuration": 7.0,
    "genre": "图文"
  },
  {
    "account": "菇菇",
    "title": "汪老笔下的“颜霸”菌子，这一抹金黄真绝！",
    "publishDate": "2026-05-07",
    "exposure": 627,
    "views": 42,
    "ctr": 0.067,
    "likes": 0,
    "comments": 0,
    "saves": 2,
    "followers": 1,
    "shares": 0,
    "avgDuration": 18.0,
    "genre": "图文"
  },
  {
    "account": "黄师傅",
    "title": "💡一张图看懂鸡油菌：森林里的金喇叭",
    "publishDate": "2026-05-05",
    "exposure": 1991,
    "views": 130,
    "ctr": 0.065,
    "likes": 5,
    "comments": 0,
    "saves": 2,
    "followers": 0,
    "shares": 1,
    "avgDuration": 13.0,
    "genre": "图文"
  },
  {
    "account": "黄师傅",
    "title": "💡一张图看懂荔枝菌：岭南第一鲜",
    "publishDate": "2026-05-04",
    "exposure": 4237,
    "views": 375,
    "ctr": 0.087,
    "likes": 3,
    "comments": 0,
    "saves": 3,
    "followers": 0,
    "shares": 2,
    "avgDuration": 12.0,
    "genre": "图文"
  },
  {
    "account": "黄师傅",
    "title": "💡一张图看懂红菇：山林里的红宝石",
    "publishDate": "2026-05-04",
    "exposure": 2882,
    "views": 157,
    "ctr": 0.054,
    "likes": 2,
    "comments": 0,
    "saves": 1,
    "followers": 1,
    "shares": 1,
    "avgDuration": 3.0,
    "genre": "图文"
  },
  {
    "account": "黄师傅",
    "title": "💡一张图看懂松茸：森林里的软黄金",
    "publishDate": "2026-05-03",
    "exposure": 2369,
    "views": 149,
    "ctr": 0.061,
    "likes": 4,
    "comments": 0,
    "saves": 3,
    "followers": 1,
    "shares": 3,
    "avgDuration": 8.0,
    "genre": "图文"
  },
  {
    "account": "黄师傅",
    "title": "💡一张图看懂鸡枞菌：白蚁造出的鲜味之王",
    "publishDate": "2026-05-03",
    "exposure": 768,
    "views": 55,
    "ctr": 0.068,
    "likes": 1,
    "comments": 2,
    "saves": 1,
    "followers": 0,
    "shares": 4,
    "avgDuration": 109.0,
    "genre": "图文"
  },
  {
    "account": "黄师傅",
    "title": "堪比现实版找茬！野生红菇的危险伪装术🍄",
    "publishDate": "2026-05-02",
    "exposure": 2927,
    "views": 278,
    "ctr": 0.093,
    "likes": 4,
    "comments": 0,
    "saves": 3,
    "followers": 1,
    "shares": 0,
    "avgDuration": 37.0,
    "genre": "图文"
  },
  {
    "account": "黄师傅",
    "title": "💡一张图看懂见手青：致幻的美味刺客",
    "publishDate": "2026-05-02",
    "exposure": 2512,
    "views": 204,
    "ctr": 0.08,
    "likes": 2,
    "comments": 0,
    "saves": 4,
    "followers": 5,
    "shares": 1,
    "avgDuration": 13.0,
    "genre": "图文"
  },
  {
    "account": "黄师傅",
    "title": "💡一张图看懂牛肝菌：餐桌上的顶级美味",
    "publishDate": "2026-05-02",
    "exposure": 2504,
    "views": 151,
    "ctr": 0.058,
    "likes": 3,
    "comments": 0,
    "saves": 4,
    "followers": 2,
    "shares": 0,
    "avgDuration": 10.0,
    "genre": "图文"
  },
  {
    "account": "黄师傅",
    "title": "🍄别再乱吃！一张图看懂野生菌美味榜",
    "publishDate": "2026-05-01",
    "exposure": 26002,
    "views": 5085,
    "ctr": 0.191,
    "likes": 32,
    "comments": 1,
    "saves": 20,
    "followers": 4,
    "shares": 9,
    "avgDuration": 14.0,
    "genre": "图文"
  },
  {
    "account": "黄师傅",
    "title": "拒绝科技狠活！干红菇真伪辨别干货✅",
    "publishDate": "2026-05-01",
    "exposure": 2959,
    "views": 230,
    "ctr": 0.077,
    "likes": 1,
    "comments": 0,
    "saves": 1,
    "followers": 1,
    "shares": 0,
    "avgDuration": 9.0,
    "genre": "图文"
  },
  {
    "account": "二胎妈",
    "title": "误食鹅膏菌怎么办",
    "publishDate": "2026-05-01",
    "exposure": 1078,
    "views": 167,
    "ctr": 0.145,
    "likes": 0,
    "comments": 0,
    "saves": 0,
    "followers": 0,
    "shares": 0,
    "avgDuration": 18.0,
    "genre": "图文"
  },
  {
    "account": "二胎妈",
    "title": "六款牛肝菌菜谱，你还有哪个没解锁？",
    "publishDate": "2026-05-01",
    "exposure": 880,
    "views": 91,
    "ctr": 0.102,
    "likes": 3,
    "comments": 1,
    "saves": 2,
    "followers": 0,
    "shares": 1,
    "avgDuration": 11.0,
    "genre": "图文"
  },
  {
    "account": "黄师傅",
    "title": "夏日餐桌MVP在此！红菇清爽滋补硬实力✅",
    "publishDate": "2026-05-01",
    "exposure": 2527,
    "views": 89,
    "ctr": 0.037,
    "likes": 1,
    "comments": 0,
    "saves": 1,
    "followers": 0,
    "shares": 0,
    "avgDuration": 5.0,
    "genre": "图文"
  },
  {
    "account": "二胎妈",
    "title": "最容易误食系列--五一特别篇",
    "publishDate": "2026-05-01",
    "exposure": 605,
    "views": 54,
    "ctr": 0.088,
    "likes": 1,
    "comments": 1,
    "saves": 1,
    "followers": 1,
    "shares": 0,
    "avgDuration": 11.0,
    "genre": "图文"
  },
  {
    "account": "黄师傅",
    "title": "餐桌上的“红衣超模”！低卡营养实力派🍄",
    "publishDate": "2026-04-30",
    "exposure": 17618,
    "views": 4066,
    "ctr": 0.226,
    "likes": 24,
    "comments": 2,
    "saves": 12,
    "followers": 4,
    "shares": 22,
    "avgDuration": 17.0,
    "genre": "图文"
  },
  {
    "account": "黄师傅",
    "title": "一张图看懂鹅膏菌：越迷人越危险的红伞伞",
    "publishDate": "2026-04-30",
    "exposure": 11119,
    "views": 1302,
    "ctr": 0.114,
    "likes": 26,
    "comments": 3,
    "saves": 17,
    "followers": 7,
    "shares": 10,
    "avgDuration": 22.0,
    "genre": "图文"
  },
  {
    "account": "黄师傅",
    "title": "💡一张图看懂白鹅膏菌：白伞伞最致命！",
    "publishDate": "2026-04-30",
    "exposure": 5940,
    "views": 698,
    "ctr": 0.115,
    "likes": 15,
    "comments": 1,
    "saves": 11,
    "followers": 2,
    "shares": 4,
    "avgDuration": 16.0,
    "genre": "图文"
  },
  {
    "account": "黄师傅",
    "title": "💡一张图看懂竹荪：火锅里的网纱仙女",
    "publishDate": "2026-04-30",
    "exposure": 3737,
    "views": 439,
    "ctr": 0.119,
    "likes": 9,
    "comments": 1,
    "saves": 8,
    "followers": 1,
    "shares": 2,
    "avgDuration": 14.0,
    "genre": "图文"
  },
  {
    "account": "菇菇",
    "title": "万菌之王怎么吃？8款松茸食谱清润养胃🍄",
    "publishDate": "2026-04-29",
    "exposure": 6544,
    "views": 955,
    "ctr": 0.145,
    "likes": 9,
    "comments": 0,
    "saves": 9,
    "followers": 0,
    "shares": 4,
    "avgDuration": 24.0,
    "genre": "图文"
  },
  {
    "account": "菇菇",
    "title": "一口尝尽山野鲜！8道荔枝菌食谱清润养胃",
    "publishDate": "2026-04-29",
    "exposure": 4510,
    "views": 682,
    "ctr": 0.147,
    "likes": 12,
    "comments": 0,
    "saves": 7,
    "followers": 1,
    "shares": 12,
    "avgDuration": 27.0,
    "genre": "图文"
  },
  {
    "account": "二胎妈",
    "title": "坐月子想喝碗羊肚菌汤，被婆婆骂败家",
    "publishDate": "2026-04-29",
    "exposure": 232,
    "views": 42,
    "ctr": 0.159,
    "likes": 0,
    "comments": 2,
    "saves": 0,
    "followers": 0,
    "shares": 0,
    "avgDuration": 6.0,
    "genre": "图文"
  },
  {
    "account": "黄师傅",
    "title": "仙气食材竹荪科普：品种分类与避坑指南✅",
    "publishDate": "2026-04-29",
    "exposure": 323,
    "views": 25,
    "ctr": 0.074,
    "likes": 0,
    "comments": 0,
    "saves": 0,
    "followers": 0,
    "shares": 1,
    "avgDuration": 23.0,
    "genre": "图文"
  },
  {
    "account": "黄师傅",
    "title": "夏秋吃菌季！野生红菇辨认与营养科普✅",
    "publishDate": "2026-04-29",
    "exposure": 323,
    "views": 23,
    "ctr": 0.068,
    "likes": 0,
    "comments": 0,
    "saves": 0,
    "followers": 0,
    "shares": 1,
    "avgDuration": 30.0,
    "genre": "图文"
  },
  {
    "account": "菇菇",
    "title": "满口爆汁的鲜！8道羊肚菌食谱益胃养人",
    "publishDate": "2026-04-29",
    "exposure": 163,
    "views": 17,
    "ctr": 0.099,
    "likes": 0,
    "comments": 1,
    "saves": 0,
    "followers": 1,
    "shares": 0,
    "avgDuration": 15.0,
    "genre": "图文"
  },
  {
    "account": "黄师傅",
    "title": "别只懂煲汤！竹荪竟是隐藏的低脂营养王者✅",
    "publishDate": "2026-04-29",
    "exposure": 69,
    "views": 6,
    "ctr": 0.103,
    "likes": 0,
    "comments": 0,
    "saves": 0,
    "followers": 0,
    "shares": 1,
    "avgDuration": 17.0,
    "genre": "图文"
  },
  {
    "account": "黄师傅",
    "title": "别只知道鲜！牛肝菌硬核营养全公开✅",
    "publishDate": "2026-04-28",
    "exposure": 1157,
    "views": 99,
    "ctr": 0.084,
    "likes": 1,
    "comments": 0,
    "saves": 1,
    "followers": 0,
    "shares": 2,
    "avgDuration": 11.0,
    "genre": "图文"
  },
  {
    "account": "菇菇",
    "title": "夏日清润天花板✨8道竹荪食谱低卡解腻",
    "publishDate": "2026-04-27",
    "exposure": 52588,
    "views": 12492,
    "ctr": 0.233,
    "likes": 188,
    "comments": 1,
    "saves": 194,
    "followers": 3,
    "shares": 94,
    "avgDuration": 33.0,
    "genre": "图文"
  },
  {
    "account": "菇菇",
    "title": "夏日清补✨8道黑松露食谱，养胃又高级",
    "publishDate": "2026-04-27",
    "exposure": 17309,
    "views": 3476,
    "ctr": 0.196,
    "likes": 63,
    "comments": 0,
    "saves": 69,
    "followers": 10,
    "shares": 36,
    "avgDuration": 23.0,
    "genre": "图文"
  },
  {
    "account": "黄师傅",
    "title": "山珍界的“鲜味炸弹”！牛肝菌挑选指南",
    "publishDate": "2026-04-27",
    "exposure": 2544,
    "views": 271,
    "ctr": 0.105,
    "likes": 2,
    "comments": 0,
    "saves": 1,
    "followers": 1,
    "shares": 1,
    "avgDuration": 16.0,
    "genre": "图文"
  },
  {
    "account": "菇菇",
    "title": "夏天少吃冰！这8道牛肝菌做法，清润又养胃",
    "publishDate": "2026-04-27",
    "exposure": 2303,
    "views": 234,
    "ctr": 0.1,
    "likes": 2,
    "comments": 0,
    "saves": 8,
    "followers": 1,
    "shares": 3,
    "avgDuration": 21.0,
    "genre": "图文"
  },
  {
    "account": "黄师傅",
    "title": "吃菌季必看！牛肝菌辨认与安全科普指南✅",
    "publishDate": "2026-04-27",
    "exposure": 1891,
    "views": 148,
    "ctr": 0.08,
    "likes": 5,
    "comments": 0,
    "saves": 4,
    "followers": 3,
    "shares": 4,
    "avgDuration": 29.0,
    "genre": "图文"
  },
  {
    "account": "黄师傅",
    "title": "一口鲜掉眉毛！牛肝菌营养科普与搭配指南✅",
    "publishDate": "2026-04-27",
    "exposure": 1221,
    "views": 54,
    "ctr": 0.045,
    "likes": 1,
    "comments": 0,
    "saves": 2,
    "followers": 1,
    "shares": 1,
    "avgDuration": 5.0,
    "genre": "图文"
  },
  {
    "account": "二胎妈",
    "title": "野生菌？一份来自大自然的馈赠！",
    "publishDate": "2026-04-27",
    "exposure": 156,
    "views": 13,
    "ctr": 0.083,
    "likes": 0,
    "comments": 0,
    "saves": 1,
    "followers": 0,
    "shares": 0,
    "avgDuration": 20.0,
    "genre": "图文"
  },
  {
    "account": "二胎妈",
    "title": "大地是有什么心事吗",
    "publishDate": "2026-04-25",
    "exposure": 451,
    "views": 74,
    "ctr": 0.164,
    "likes": 1,
    "comments": 1,
    "saves": 0,
    "followers": 0,
    "shares": 0,
    "avgDuration": 20.0,
    "genre": "图文"
  },
  {
    "account": "黄师傅",
    "title": "云南神仙野菌！让人又爱又恨的见手青",
    "publishDate": "2026-04-24",
    "exposure": 37869,
    "views": 7894,
    "ctr": 0.208,
    "likes": 35,
    "comments": 2,
    "saves": 23,
    "followers": 3,
    "shares": 47,
    "avgDuration": 18.0,
    "genre": "图文"
  },
  {
    "account": "菇菇",
    "title": "内调好气色！这8道野生菌滋补汤配方收好",
    "publishDate": "2026-04-24",
    "exposure": 3152,
    "views": 283,
    "ctr": 0.09,
    "likes": 13,
    "comments": 2,
    "saves": 17,
    "followers": 6,
    "shares": 4,
    "avgDuration": 28.0,
    "genre": "图文"
  },
  {
    "account": "二胎妈",
    "title": "一家子个人想过去体验挖菌子",
    "publishDate": "2026-04-23",
    "exposure": 943,
    "views": 132,
    "ctr": 0.136,
    "likes": 2,
    "comments": 29,
    "saves": 0,
    "followers": 1,
    "shares": 0,
    "avgDuration": 10.0,
    "genre": "图文"
  },
  {
    "account": "二胎妈",
    "title": "菌子人账号建议",
    "publishDate": "2026-04-23",
    "exposure": 378,
    "views": 42,
    "ctr": 0.108,
    "likes": 0,
    "comments": 3,
    "saves": 0,
    "followers": 1,
    "shares": 0,
    "avgDuration": 15.0,
    "genre": "图文"
  },
  {
    "account": "二胎妈",
    "title": "图片拍起来太暗……但是",
    "publishDate": "2026-04-23",
    "exposure": 202,
    "views": 23,
    "ctr": 0.119,
    "likes": 1,
    "comments": 1,
    "saves": 0,
    "followers": 0,
    "shares": 0,
    "avgDuration": 7.0,
    "genre": "图文"
  },
  {
    "account": "18",
    "title": "年度MVP菌子结算时刻！",
    "publishDate": "2026-04-22",
    "exposure": 178,
    "views": 5,
    "ctr": 0.023,
    "likes": 0,
    "comments": 0,
    "saves": 1,
    "followers": 1,
    "shares": 0,
    "avgDuration": 4.0,
    "genre": "视频"
  },
  {
    "account": "黄师傅",
    "title": "见手青变色不是有毒",
    "publishDate": "2026-04-17",
    "exposure": 1026,
    "views": 221,
    "ctr": 0.083,
    "likes": 3,
    "comments": 0,
    "saves": 1,
    "followers": 1,
    "shares": 0,
    "avgDuration": 19.0,
    "genre": "视频"
  },
  {
    "account": "黄师傅",
    "title": "吃生的见小人 吃熟的防小人",
    "publishDate": "2026-04-16",
    "exposure": 1970,
    "views": 431,
    "ctr": 0.136,
    "likes": 8,
    "comments": 0,
    "saves": 5,
    "followers": 5,
    "shares": 0,
    "avgDuration": 5.0,
    "genre": "视频"
  },
  {
    "account": "菇菇",
    "title": "刷了90个荔枝菌后我悟了，但已经来不及了",
    "publishDate": "2026-04-16",
    "exposure": 2008,
    "views": 128,
    "ctr": 0.064,
    "likes": 3,
    "comments": 0,
    "saves": 2,
    "followers": 0,
    "shares": 2,
    "avgDuration": 10.0,
    "genre": "图文"
  },
  {
    "account": "黄师傅",
    "title": "见手青90%要注意的环节",
    "publishDate": "2026-04-15",
    "exposure": 1379,
    "views": 240,
    "ctr": 0.078,
    "likes": 1,
    "comments": 2,
    "saves": 0,
    "followers": 1,
    "shares": 0,
    "avgDuration": 11.0,
    "genre": "视频"
  },
  {
    "account": "菇菇",
    "title": "答应我！要试这碗鲜到掉眉毛的鸡汤面",
    "publishDate": "2026-04-15",
    "exposure": 2187,
    "views": 154,
    "ctr": 0.07,
    "likes": 2,
    "comments": 0,
    "saves": 0,
    "followers": 1,
    "shares": 0,
    "avgDuration": 5.0,
    "genre": "图文"
  },
  {
    "account": "菇菇",
    "title": "鲜到舔盘！春日必吃的羊肚菌神仙三件套",
    "publishDate": "2026-04-14",
    "exposure": 2165,
    "views": 198,
    "ctr": 0.092,
    "likes": 2,
    "comments": 0,
    "saves": 4,
    "followers": 0,
    "shares": 0,
    "avgDuration": 15.0,
    "genre": "图文"
  },
  {
    "account": "菇菇",
    "title": "0失败！羊肚菌蒸蛋嫩过布丁的秘密",
    "publishDate": "2026-04-13",
    "exposure": 1420,
    "views": 89,
    "ctr": 0.065,
    "likes": 3,
    "comments": 0,
    "saves": 0,
    "followers": 0,
    "shares": 1,
    "avgDuration": 11.0,
    "genre": "图文"
  },
  {
    "account": "菇菇",
    "title": "焖饭+炒腊肠｜简单又鲜掉眉毛",
    "publishDate": "2026-04-13",
    "exposure": 545,
    "views": 39,
    "ctr": 0.07,
    "likes": 0,
    "comments": 0,
    "saves": 0,
    "followers": 0,
    "shares": 0,
    "avgDuration": 7.0,
    "genre": "图文"
  },
  {
    "account": "菇菇",
    "title": "又怕又爱吃的“神仙毒物”",
    "publishDate": "2026-04-11",
    "exposure": 431,
    "views": 40,
    "ctr": 0.086,
    "likes": 0,
    "comments": 0,
    "saves": 0,
    "followers": 0,
    "shares": 1,
    "avgDuration": 6.0,
    "genre": "图文"
  },
  {
    "account": "菇菇",
    "title": "荔枝菌一辈子要吃上一次",
    "publishDate": "2026-04-10",
    "exposure": 5480,
    "views": 1270,
    "ctr": 0.221,
    "likes": 2,
    "comments": 0,
    "saves": 1,
    "followers": 0,
    "shares": 16,
    "avgDuration": 14.0,
    "genre": "图文"
  },
  {
    "account": "二胎妈",
    "title": "怎样辨别真假，这步做对赚大了",
    "publishDate": "2026-04-07",
    "exposure": 107,
    "views": 6,
    "ctr": 0.029,
    "likes": 0,
    "comments": 0,
    "saves": 0,
    "followers": 0,
    "shares": 0,
    "avgDuration": 11.0,
    "genre": "视频"
  },
  {
    "account": "18",
    "title": "假货特征图解，正确方法在这",
    "publishDate": "2026-04-07",
    "exposure": 74,
    "views": 3,
    "ctr": 0.027,
    "likes": 0,
    "comments": 0,
    "saves": 0,
    "followers": 0,
    "shares": 0,
    "avgDuration": 11.0,
    "genre": "视频"
  },
  {
    "account": "二胎妈",
    "title": "吃多会上火吗，转发家人受益",
    "publishDate": "2026-04-06",
    "exposure": 56,
    "views": 4,
    "ctr": 0.0,
    "likes": 0,
    "comments": 0,
    "saves": 0,
    "followers": 0,
    "shares": 0,
    "avgDuration": 5.0,
    "genre": "视频"
  },
  {
    "account": "二胎妈",
    "title": "4步鉴别真伪，老中医经验分享",
    "publishDate": "2026-04-06",
    "exposure": 76,
    "views": 4,
    "ctr": 0.0,
    "likes": 0,
    "comments": 0,
    "saves": 0,
    "followers": 0,
    "shares": 1,
    "avgDuration": 6.0,
    "genre": "视频"
  },
  {
    "account": "18",
    "title": "手术后能吃吗，这秘密90%人不知道",
    "publishDate": "2026-04-06",
    "exposure": 73,
    "views": 3,
    "ctr": 0.014,
    "likes": 0,
    "comments": 0,
    "saves": 0,
    "followers": 0,
    "shares": 0,
    "avgDuration": 4.0,
    "genre": "视频"
  },
  {
    "account": "18",
    "title": "最佳进补季节，实测数据告诉你",
    "publishDate": "2026-04-06",
    "exposure": 61,
    "views": 2,
    "ctr": 0.033,
    "likes": 0,
    "comments": 0,
    "saves": 0,
    "followers": 0,
    "shares": 0,
    "avgDuration": 1.0,
    "genre": "视频"
  },
  {
    "account": "二胎妈",
    "title": "感冒能喝吗，附详细步骤数据",
    "publishDate": "2026-04-05",
    "exposure": 105,
    "views": 9,
    "ctr": 0.02,
    "likes": 1,
    "comments": 0,
    "saves": 0,
    "followers": 0,
    "shares": 0,
    "avgDuration": 5.0,
    "genre": "视频"
  },
  {
    "account": "18",
    "title": "一年吃几次有效，做错等于白花钱",
    "publishDate": "2026-04-05",
    "exposure": 57,
    "views": 0,
    "ctr": 0.0,
    "likes": 0,
    "comments": 0,
    "saves": 0,
    "followers": 0,
    "shares": 0,
    "avgDuration": 0.0,
    "genre": "视频"
  },
  {
    "account": "18",
    "title": "间隔多久安全，建议收藏备用",
    "publishDate": "2026-04-05",
    "exposure": 70,
    "views": 0,
    "ctr": 0.0,
    "likes": 0,
    "comments": 0,
    "saves": 0,
    "followers": 0,
    "shares": 0,
    "avgDuration": 0.0,
    "genre": "视频"
  },
  {
    "account": "二胎妈",
    "title": "出锅前加最合适，避坑指南必看",
    "publishDate": "2026-04-04",
    "exposure": 164,
    "views": 9,
    "ctr": 0.031,
    "likes": 0,
    "comments": 0,
    "saves": 0,
    "followers": 0,
    "shares": 0,
    "avgDuration": 2.0,
    "genre": "视频"
  },
  {
    "account": "二胎妈",
    "title": "海鲜相克食物，简单实用接地气",
    "publishDate": "2026-04-04",
    "exposure": 58,
    "views": 5,
    "ctr": 0.0,
    "likes": 1,
    "comments": 0,
    "saves": 0,
    "followers": 0,
    "shares": 0,
    "avgDuration": 5.0,
    "genre": "视频"
  },
  {
    "account": "18",
    "title": "孕妇喝了会怎样，收藏备用不亏",
    "publishDate": "2026-04-04",
    "exposure": 59,
    "views": 2,
    "ctr": 0.034,
    "likes": 0,
    "comments": 0,
    "saves": 0,
    "followers": 0,
    "shares": 0,
    "avgDuration": 2.0,
    "genre": "视频"
  },
  {
    "account": "二胎妈",
    "title": "恢复期怎麼补，转发家人受益",
    "publishDate": "2026-04-03",
    "exposure": 64,
    "views": 7,
    "ctr": 0.066,
    "likes": 1,
    "comments": 1,
    "saves": 1,
    "followers": 0,
    "shares": 0,
    "avgDuration": 5.0,
    "genre": "视频"
  },
  {
    "account": "二胎妈",
    "title": "加盐时机，赶紧告诉家人",
    "publishDate": "2026-04-03",
    "exposure": 42,
    "views": 1,
    "ctr": 0.0,
    "likes": 0,
    "comments": 0,
    "saves": 0,
    "followers": 0,
    "shares": 0,
    "avgDuration": 1.0,
    "genre": "视频"
  },
  {
    "account": "18",
    "title": "早加盐蛋白质凝固，收藏备用不亏",
    "publishDate": "2026-04-03",
    "exposure": 50,
    "views": 0,
    "ctr": 0.0,
    "likes": 0,
    "comments": 0,
    "saves": 0,
    "followers": 0,
    "shares": 0,
    "avgDuration": 0.0,
    "genre": "视频"
  },
  {
    "account": "18",
    "title": "术后进补注意，收藏级教程",
    "publishDate": "2026-04-03",
    "exposure": 69,
    "views": 0,
    "ctr": 0.0,
    "likes": 0,
    "comments": 0,
    "saves": 0,
    "followers": 0,
    "shares": 0,
    "avgDuration": 0.0,
    "genre": "视频"
  },
  {
    "account": "二胎妈",
    "title": "泡发次数最佳方案",
    "publishDate": "2026-04-02",
    "exposure": 140,
    "views": 19,
    "ctr": 0.103,
    "likes": 0,
    "comments": 0,
    "saves": 0,
    "followers": 0,
    "shares": 0,
    "avgDuration": 4.0,
    "genre": "视频"
  },
  {
    "account": "二胎妈",
    "title": "容器选择影响泡发效果",
    "publishDate": "2026-04-02",
    "exposure": 91,
    "views": 7,
    "ctr": 0.056,
    "likes": 0,
    "comments": 0,
    "saves": 0,
    "followers": 0,
    "shares": 0,
    "avgDuration": 9.0,
    "genre": "视频"
  },
  {
    "account": "二胎妈",
    "title": "冷水下锅还是热水，再晚来不及了",
    "publishDate": "2026-04-02",
    "exposure": 170,
    "views": 6,
    "ctr": 0.024,
    "likes": 0,
    "comments": 0,
    "saves": 0,
    "followers": 0,
    "shares": 0,
    "avgDuration": 3.0,
    "genre": "视频"
  },
  {
    "account": "二胎妈",
    "title": "羊肚菌泡发保姆级教程",
    "publishDate": "2026-04-02",
    "exposure": 76,
    "views": 5,
    "ctr": 0.041,
    "likes": 0,
    "comments": 0,
    "saves": 0,
    "followers": 0,
    "shares": 0,
    "avgDuration": 3.0,
    "genre": "视频"
  },
  {
    "account": "二胎妈",
    "title": "泡发问题全解析",
    "publishDate": "2026-04-02",
    "exposure": 65,
    "views": 5,
    "ctr": 0.063,
    "likes": 0,
    "comments": 0,
    "saves": 0,
    "followers": 0,
    "shares": 0,
    "avgDuration": 1.0,
    "genre": "视频"
  },
  {
    "account": "二胎妈",
    "title": "泡发5大误区早知道",
    "publishDate": "2026-04-02",
    "exposure": 76,
    "views": 3,
    "ctr": 0.014,
    "likes": 0,
    "comments": 0,
    "saves": 0,
    "followers": 0,
    "shares": 0,
    "avgDuration": 3.0,
    "genre": "视频"
  },
  {
    "account": "18",
    "title": "热水下锅肉质变柴，附详细步骤数据",
    "publishDate": "2026-04-02",
    "exposure": 83,
    "views": 2,
    "ctr": 0.012,
    "likes": 0,
    "comments": 0,
    "saves": 0,
    "followers": 0,
    "shares": 0,
    "avgDuration": 2.0,
    "genre": "视频"
  },
  {
    "account": "18",
    "title": "竹荪泡水别乱来",
    "publishDate": "2026-03-30",
    "exposure": 44,
    "views": 20,
    "ctr": 0.111,
    "likes": 0,
    "comments": 0,
    "saves": 0,
    "followers": 0,
    "shares": 0,
    "avgDuration": 11.0,
    "genre": "视频"
  },
  {
    "account": "二胎妈",
    "title": "竹荪能毒死人？",
    "publishDate": "2026-03-30",
    "exposure": 327,
    "views": 20,
    "ctr": 0.025,
    "likes": 0,
    "comments": 0,
    "saves": 0,
    "followers": 0,
    "shares": 0,
    "avgDuration": 3.0,
    "genre": "视频"
  },
  {
    "account": "18",
    "title": "竹荪的泡水艺术",
    "publishDate": "2026-03-30",
    "exposure": 46,
    "views": 17,
    "ctr": 0.063,
    "likes": 0,
    "comments": 0,
    "saves": 0,
    "followers": 0,
    "shares": 0,
    "avgDuration": 4.0,
    "genre": "视频"
  },
  {
    "account": "二胎妈",
    "title": "竹荪泡水就废了？",
    "publishDate": "2026-03-30",
    "exposure": 179,
    "views": 9,
    "ctr": 0.045,
    "likes": 0,
    "comments": 0,
    "saves": 0,
    "followers": 0,
    "shares": 0,
    "avgDuration": 4.0,
    "genre": "视频"
  },
  {
    "account": "二胎妈",
    "title": "竹荪泡水正确方法",
    "publishDate": "2026-03-30",
    "exposure": 192,
    "views": 8,
    "ctr": 0.021,
    "likes": 0,
    "comments": 0,
    "saves": 0,
    "followers": 0,
    "shares": 0,
    "avgDuration": 5.0,
    "genre": "视频"
  },
  {
    "account": "18",
    "title": "竹荪的价值密码",
    "publishDate": "2026-03-30",
    "exposure": 123,
    "views": 7,
    "ctr": 0.017,
    "likes": 0,
    "comments": 0,
    "saves": 0,
    "followers": 0,
    "shares": 0,
    "avgDuration": 40.0,
    "genre": "视频"
  },
  {
    "account": "18",
    "title": "竹荪为啥这么贵？",
    "publishDate": "2026-03-29",
    "exposure": 224,
    "views": 41,
    "ctr": 0.058,
    "likes": 1,
    "comments": 0,
    "saves": 0,
    "followers": 0,
    "shares": 0,
    "avgDuration": 3.0,
    "genre": "视频"
  },
  {
    "account": "二胎妈",
    "title": "竹荪比肉还贵？",
    "publishDate": "2026-03-29",
    "exposure": 366,
    "views": 40,
    "ctr": 0.027,
    "likes": 0,
    "comments": 0,
    "saves": 0,
    "followers": 0,
    "shares": 0,
    "avgDuration": 8.0,
    "genre": "视频"
  },
  {
    "account": "二胎妈",
    "title": "竹荪价格大揭秘",
    "publishDate": "2026-03-29",
    "exposure": 55,
    "views": 27,
    "ctr": 0.034,
    "likes": 0,
    "comments": 0,
    "saves": 0,
    "followers": 0,
    "shares": 0,
    "avgDuration": 1.0,
    "genre": "视频"
  },
  {
    "account": "18",
    "title": "竹荪的身份之谜",
    "publishDate": "2026-03-29",
    "exposure": 41,
    "views": 19,
    "ctr": 0.08,
    "likes": 0,
    "comments": 0,
    "saves": 0,
    "followers": 0,
    "shares": 0,
    "avgDuration": 2.0,
    "genre": "视频"
  },
  {
    "account": "二胎妈",
    "title": "竹荪的植物与真菌之争",
    "publishDate": "2026-03-29",
    "exposure": 59,
    "views": 16,
    "ctr": 0.0,
    "likes": 0,
    "comments": 0,
    "saves": 0,
    "followers": 0,
    "shares": 0,
    "avgDuration": 7.0,
    "genre": "视频"
  },
  {
    "account": "二胎妈",
    "title": "竹荪是植物还是菌？",
    "publishDate": "2026-03-29",
    "exposure": 73,
    "views": 12,
    "ctr": 0.016,
    "likes": 0,
    "comments": 0,
    "saves": 0,
    "followers": 0,
    "shares": 0,
    "avgDuration": 12.0,
    "genre": "视频"
  },
  {
    "account": "18",
    "title": "竹荪到底是个啥？",
    "publishDate": "2026-03-29",
    "exposure": 35,
    "views": 11,
    "ctr": 0.04,
    "likes": 0,
    "comments": 0,
    "saves": 0,
    "followers": 0,
    "shares": 0,
    "avgDuration": 1.0,
    "genre": "视频"
  },
  {
    "account": "二胎妈",
    "title": "为了守住大山的菌，我来了！",
    "publishDate": "2026-03-28",
    "exposure": 1395,
    "views": 397,
    "ctr": 0.056,
    "likes": 0,
    "comments": 0,
    "saves": 0,
    "followers": 0,
    "shares": 0,
    "avgDuration": 2.0,
    "genre": "视频"
  },
  {
    "account": "二胎妈",
    "title": "挖蘑菇啦，有收获吗",
    "publishDate": "2026-03-28",
    "exposure": 547,
    "views": 50,
    "ctr": 0.067,
    "likes": 1,
    "comments": 0,
    "saves": 0,
    "followers": 0,
    "shares": 0,
    "avgDuration": 17.0,
    "genre": "视频"
  },
  {
    "account": "二胎妈",
    "title": "错过了就需要再等一年了",
    "publishDate": "2026-03-28",
    "exposure": 52,
    "views": 11,
    "ctr": 0.0,
    "likes": 0,
    "comments": 0,
    "saves": 0,
    "followers": 0,
    "shares": 0,
    "avgDuration": 5.0,
    "genre": "视频"
  },
  {
    "account": "二胎妈",
    "title": "生活太苦的时候、你该喝点汤",
    "publishDate": "2026-03-28",
    "exposure": 124,
    "views": 10,
    "ctr": 0.081,
    "likes": 0,
    "comments": 0,
    "saves": 0,
    "followers": 0,
    "shares": 0,
    "avgDuration": 27.0,
    "genre": "视频"
  },
  {
    "account": "二胎妈",
    "title": "雨后山里的菌菇、是大自然的馈赠",
    "publishDate": "2026-03-27",
    "exposure": 534,
    "views": 83,
    "ctr": 0.118,
    "likes": 0,
    "comments": 0,
    "saves": 0,
    "followers": 0,
    "shares": 0,
    "avgDuration": 1.0,
    "genre": "视频"
  },
  {
    "account": "18",
    "title": "耶~亲自采摘羊肚菌咯",
    "publishDate": "2026-03-27",
    "exposure": 544,
    "views": 61,
    "ctr": 0.048,
    "likes": 3,
    "comments": 0,
    "saves": 0,
    "followers": 0,
    "shares": 0,
    "avgDuration": 19.0,
    "genre": "视频"
  },
  {
    "account": "二胎妈",
    "title": "鸡枞菌，一年只有一季，你吃过吗？",
    "publishDate": "2026-03-27",
    "exposure": 362,
    "views": 47,
    "ctr": 0.11,
    "likes": 0,
    "comments": 0,
    "saves": 0,
    "followers": 1,
    "shares": 0,
    "avgDuration": 12.0,
    "genre": "视频"
  },
  {
    "account": "18",
    "title": "体验了割羊肚菌活动",
    "publishDate": "2026-03-27",
    "exposure": 387,
    "views": 34,
    "ctr": 0.091,
    "likes": 0,
    "comments": 0,
    "saves": 0,
    "followers": 0,
    "shares": 0,
    "avgDuration": 6.0,
    "genre": "视频"
  },
  {
    "account": "二胎妈",
    "title": "这菇菇真的太好吃了",
    "publishDate": "2026-03-27",
    "exposure": 152,
    "views": 5,
    "ctr": 0.013,
    "likes": 0,
    "comments": 0,
    "saves": 0,
    "followers": 0,
    "shares": 0,
    "avgDuration": 13.0,
    "genre": "视频"
  },
  {
    "account": "二胎妈",
    "title": "【宝子们，来！】喝汤啦！",
    "publishDate": "2026-03-27",
    "exposure": 141,
    "views": 2,
    "ctr": 0.007,
    "likes": 0,
    "comments": 0,
    "saves": 0,
    "followers": 0,
    "shares": 0,
    "avgDuration": 3.0,
    "genre": "视频"
  },
  {
    "account": "18",
    "title": "🎉在小红书获得的阅读量破2000啦❗️",
    "publishDate": "2026-03-27",
    "exposure": 51,
    "views": 0,
    "ctr": 0.0,
    "likes": 0,
    "comments": 0,
    "saves": 0,
    "followers": 0,
    "shares": 0,
    "avgDuration": 0.0,
    "genre": "图文"
  },
  {
    "account": "二胎妈",
    "title": "鸡枞菌满满的一天",
    "publishDate": "2026-03-26",
    "exposure": 929,
    "views": 50,
    "ctr": 0.053,
    "likes": 1,
    "comments": 0,
    "saves": 0,
    "followers": 0,
    "shares": 0,
    "avgDuration": 1.0,
    "genre": "视频"
  },
  {
    "account": "二胎妈",
    "title": "每一位热爱生活得情书",
    "publishDate": "2026-03-26",
    "exposure": 238,
    "views": 10,
    "ctr": 0.03,
    "likes": 1,
    "comments": 0,
    "saves": 0,
    "followers": 0,
    "shares": 0,
    "avgDuration": 3.0,
    "genre": "视频"
  },
  {
    "account": "二胎妈",
    "title": "每一位煲汤人士的爱好",
    "publishDate": "2026-03-26",
    "exposure": 115,
    "views": 10,
    "ctr": 0.079,
    "likes": 0,
    "comments": 0,
    "saves": 0,
    "followers": 0,
    "shares": 0,
    "avgDuration": 4.0,
    "genre": "视频"
  },
  {
    "account": "18",
    "title": "快看，我发明了新的羊肚菌处理方法！",
    "publishDate": "2026-03-26",
    "exposure": 166,
    "views": 8,
    "ctr": 0.031,
    "likes": 0,
    "comments": 0,
    "saves": 0,
    "followers": 0,
    "shares": 0,
    "avgDuration": 11.0,
    "genre": "视频"
  },
  {
    "account": "二胎妈",
    "title": "羊肚菌刀工展示！每个动作都清晰",
    "publishDate": "2026-03-26",
    "exposure": 141,
    "views": 8,
    "ctr": 0.044,
    "likes": 0,
    "comments": 0,
    "saves": 0,
    "followers": 0,
    "shares": 0,
    "avgDuration": 2.0,
    "genre": "视频"
  },
  {
    "account": "18",
    "title": "羊肚菌的飘香，苏格拉底也动心",
    "publishDate": "2026-03-26",
    "exposure": 151,
    "views": 3,
    "ctr": 0.02,
    "likes": 0,
    "comments": 0,
    "saves": 0,
    "followers": 0,
    "shares": 0,
    "avgDuration": 6.0,
    "genre": "视频"
  },
  {
    "account": "二胎妈",
    "title": "在深山了寻找那一抹安宁",
    "publishDate": "2026-03-25",
    "exposure": 158,
    "views": 24,
    "ctr": 0.063,
    "likes": 0,
    "comments": 0,
    "saves": 0,
    "followers": 0,
    "shares": 0,
    "avgDuration": 33.0,
    "genre": "视频"
  },
  {
    "account": "二胎妈",
    "title": "比一般的菌菇有着更好的口感",
    "publishDate": "2026-03-25",
    "exposure": 164,
    "views": 20,
    "ctr": 0.101,
    "likes": 0,
    "comments": 0,
    "saves": 0,
    "followers": 0,
    "shares": 0,
    "avgDuration": 27.0,
    "genre": "视频"
  },
  {
    "account": "18",
    "title": "羊肚菌做羹，切记别放这物",
    "publishDate": "2026-03-25",
    "exposure": 241,
    "views": 7,
    "ctr": 0.021,
    "likes": 0,
    "comments": 0,
    "saves": 0,
    "followers": 0,
    "shares": 0,
    "avgDuration": 5.0,
    "genre": "视频"
  },
  {
    "account": "18",
    "title": "羊肚菌加它，鲜味放大十倍",
    "publishDate": "2026-03-25",
    "exposure": 153,
    "views": 2,
    "ctr": 0.007,
    "likes": 0,
    "comments": 0,
    "saves": 0,
    "followers": 0,
    "shares": 0,
    "avgDuration": 10.0,
    "genre": "视频"
  },
  {
    "account": "18",
    "title": "5分钟，搞定星级滋补浓羹",
    "publishDate": "2026-03-25",
    "exposure": 148,
    "views": 2,
    "ctr": 0.014,
    "likes": 0,
    "comments": 0,
    "saves": 0,
    "followers": 0,
    "shares": 0,
    "avgDuration": 25.0,
    "genre": "视频"
  },
  {
    "account": "二胎妈",
    "title": "这种每年都难采集的菌菇你吃过吗？",
    "publishDate": "2026-03-25",
    "exposure": 36,
    "views": 2,
    "ctr": 0.029,
    "likes": 0,
    "comments": 0,
    "saves": 0,
    "followers": 0,
    "shares": 0,
    "avgDuration": 39.0,
    "genre": "视频"
  },
  {
    "account": "18",
    "title": "体虚没力气？这碗浓羹救命",
    "publishDate": "2026-03-25",
    "exposure": 72,
    "views": 0,
    "ctr": 0.0,
    "likes": 0,
    "comments": 0,
    "saves": 0,
    "followers": 0,
    "shares": 0,
    "avgDuration": 0.0,
    "genre": "视频"
  },
  {
    "account": "18",
    "title": "羊肚菌这样吃才不浪费",
    "publishDate": "2026-03-24",
    "exposure": 429,
    "views": 72,
    "ctr": 0.055,
    "likes": 0,
    "comments": 0,
    "saves": 0,
    "followers": 0,
    "shares": 0,
    "avgDuration": 9.0,
    "genre": "视频"
  },
  {
    "account": "18",
    "title": "羊肚菌别乱吃,老铁们",
    "publishDate": "2026-03-24",
    "exposure": 432,
    "views": 56,
    "ctr": 0.05,
    "likes": 1,
    "comments": 0,
    "saves": 0,
    "followers": 0,
    "shares": 0,
    "avgDuration": 21.0,
    "genre": "视频"
  },
  {
    "account": "二胎妈",
    "title": "海参的正确吃法",
    "publishDate": "2026-03-24",
    "exposure": 188,
    "views": 21,
    "ctr": 0.035,
    "likes": 0,
    "comments": 0,
    "saves": 0,
    "followers": 0,
    "shares": 0,
    "avgDuration": 7.0,
    "genre": "视频"
  },
  {
    "account": "二胎妈",
    "title": "让人解压治愈的海参",
    "publishDate": "2026-03-24",
    "exposure": 186,
    "views": 12,
    "ctr": 0.039,
    "likes": 0,
    "comments": 0,
    "saves": 0,
    "followers": 0,
    "shares": 0,
    "avgDuration": 4.0,
    "genre": "视频"
  },
  {
    "account": "18",
    "title": "招待贵客，压轴就上这碗羹",
    "publishDate": "2026-03-24",
    "exposure": 354,
    "views": 9,
    "ctr": 0.023,
    "likes": 1,
    "comments": 0,
    "saves": 0,
    "followers": 0,
    "shares": 0,
    "avgDuration": 3.0,
    "genre": "视频"
  },
  {
    "account": "二胎妈",
    "title": "下海捡海参",
    "publishDate": "2026-03-24",
    "exposure": 174,
    "views": 6,
    "ctr": 0.029,
    "likes": 0,
    "comments": 0,
    "saves": 0,
    "followers": 0,
    "shares": 0,
    "avgDuration": 3.0,
    "genre": "视频"
  },
  {
    "account": "二胎妈",
    "title": "厨房里解压的食材",
    "publishDate": "2026-03-24",
    "exposure": 124,
    "views": 6,
    "ctr": 0.025,
    "likes": 0,
    "comments": 0,
    "saves": 0,
    "followers": 0,
    "shares": 0,
    "avgDuration": 4.0,
    "genre": "视频"
  },
  {
    "account": "18",
    "title": "几块钱，喝出燕窝的高级感",
    "publishDate": "2026-03-24",
    "exposure": 135,
    "views": 5,
    "ctr": 0.03,
    "likes": 0,
    "comments": 0,
    "saves": 0,
    "followers": 0,
    "shares": 0,
    "avgDuration": 9.0,
    "genre": "视频"
  },
  {
    "account": "二胎妈",
    "title": "高蛋白质，肥大软体",
    "publishDate": "2026-03-24",
    "exposure": 199,
    "views": 2,
    "ctr": 0.01,
    "likes": 0,
    "comments": 0,
    "saves": 0,
    "followers": 0,
    "shares": 0,
    "avgDuration": 33.0,
    "genre": "视频"
  },
  {
    "account": "二胎妈",
    "title": "品质的铁证明",
    "publishDate": "2026-03-24",
    "exposure": 122,
    "views": 1,
    "ctr": 0.008,
    "likes": 0,
    "comments": 0,
    "saves": 0,
    "followers": 0,
    "shares": 0,
    "avgDuration": 7.0,
    "genre": "视频"
  },
  {
    "account": "二胎妈",
    "title": "泡发好的海参长这样",
    "publishDate": "2026-03-23",
    "exposure": 358,
    "views": 140,
    "ctr": 0.047,
    "likes": 0,
    "comments": 0,
    "saves": 0,
    "followers": 0,
    "shares": 0,
    "avgDuration": 8.0,
    "genre": "视频"
  },
  {
    "account": "二胎妈",
    "title": "今天来点海参～",
    "publishDate": "2026-03-23",
    "exposure": 88,
    "views": 27,
    "ctr": 0.093,
    "likes": 1,
    "comments": 0,
    "saves": 1,
    "followers": 0,
    "shares": 0,
    "avgDuration": 6.0,
    "genre": "视频"
  },
  {
    "account": "二胎妈",
    "title": "被这碗海参汤硬控了！",
    "publishDate": "2026-03-23",
    "exposure": 146,
    "views": 15,
    "ctr": 0.022,
    "likes": 0,
    "comments": 0,
    "saves": 0,
    "followers": 0,
    "shares": 0,
    "avgDuration": 9.0,
    "genre": "视频"
  },
  {
    "account": "二胎妈",
    "title": "即食的海参方便犒劳自己",
    "publishDate": "2026-03-23",
    "exposure": 121,
    "views": 14,
    "ctr": 0.069,
    "likes": 0,
    "comments": 0,
    "saves": 0,
    "followers": 0,
    "shares": 0,
    "avgDuration": 1.0,
    "genre": "视频"
  },
  {
    "account": "18",
    "title": "羊肚菌颜色越深越好？大错特错！",
    "publishDate": "2026-03-23",
    "exposure": 341,
    "views": 13,
    "ctr": 0.035,
    "likes": 1,
    "comments": 0,
    "saves": 0,
    "followers": 0,
    "shares": 0,
    "avgDuration": 9.0,
    "genre": "视频"
  },
  {
    "account": "18",
    "title": "炖鸡汤可不能少了这个",
    "publishDate": "2026-03-23",
    "exposure": 218,
    "views": 7,
    "ctr": 0.009,
    "likes": 0,
    "comments": 0,
    "saves": 0,
    "followers": 0,
    "shares": 0,
    "avgDuration": 3.0,
    "genre": "视频"
  },
  {
    "account": "18",
    "title": "怕胖又想补蛋白质的人看过来",
    "publishDate": "2026-03-23",
    "exposure": 121,
    "views": 7,
    "ctr": 0.042,
    "likes": 0,
    "comments": 0,
    "saves": 0,
    "followers": 0,
    "shares": 0,
    "avgDuration": 4.0,
    "genre": "视频"
  },
  {
    "account": "18",
    "title": "不可贪吃过多，要适量而食",
    "publishDate": "2026-03-23",
    "exposure": 253,
    "views": 6,
    "ctr": 0.024,
    "likes": 0,
    "comments": 0,
    "saves": 0,
    "followers": 0,
    "shares": 0,
    "avgDuration": 7.0,
    "genre": "视频"
  },
  {
    "account": "二胎妈",
    "title": "中式养生：晨起一碗滋补粥🥣",
    "publishDate": "2026-03-23",
    "exposure": 273,
    "views": 4,
    "ctr": 0.004,
    "likes": 0,
    "comments": 0,
    "saves": 0,
    "followers": 0,
    "shares": 0,
    "avgDuration": 2.0,
    "genre": "视频"
  },
  {
    "account": "18",
    "title": "好吃的鸡蛋羹秘籍来了",
    "publishDate": "2026-03-23",
    "exposure": 285,
    "views": 3,
    "ctr": 0.011,
    "likes": 0,
    "comments": 0,
    "saves": 0,
    "followers": 0,
    "shares": 0,
    "avgDuration": 4.0,
    "genre": "视频"
  },
  {
    "account": "二胎妈",
    "title": "干货的海参有尝试过吗",
    "publishDate": "2026-03-23",
    "exposure": 38,
    "views": 1,
    "ctr": 0.026,
    "likes": 0,
    "comments": 0,
    "saves": 0,
    "followers": 0,
    "shares": 0,
    "avgDuration": 4.0,
    "genre": "视频"
  },
  {
    "account": "二胎妈",
    "title": "‼️海参：纪大成未弱 消",
    "publishDate": "2026-03-23",
    "exposure": 106,
    "views": 0,
    "ctr": 0.0,
    "likes": 0,
    "comments": 0,
    "saves": 0,
    "followers": 0,
    "shares": 0,
    "avgDuration": 0.0,
    "genre": "视频"
  },
  {
    "account": "18",
    "title": "这样采摘羊肚菌不伤根！",
    "publishDate": "2026-03-22",
    "exposure": 1105,
    "views": 95,
    "ctr": 0.059,
    "likes": 1,
    "comments": 0,
    "saves": 0,
    "followers": 0,
    "shares": 0,
    "avgDuration": 9.0,
    "genre": "视频"
  },
  {
    "account": "二胎妈",
    "title": "海参的美味你不想来尝尝吗？",
    "publishDate": "2026-03-22",
    "exposure": 188,
    "views": 52,
    "ctr": 0.029,
    "likes": 1,
    "comments": 0,
    "saves": 1,
    "followers": 0,
    "shares": 0,
    "avgDuration": 20.0,
    "genre": "视频"
  },
  {
    "account": "二胎妈",
    "title": "越吃越漂亮的诀窍",
    "publishDate": "2026-03-22",
    "exposure": 433,
    "views": 40,
    "ctr": 0.066,
    "likes": 0,
    "comments": 0,
    "saves": 0,
    "followers": 0,
    "shares": 0,
    "avgDuration": 5.0,
    "genre": "视频"
  },
  {
    "account": "18",
    "title": "羊肚菌表面的泥很难洗？那是没用对方法！",
    "publishDate": "2026-03-22",
    "exposure": 317,
    "views": 25,
    "ctr": 0.068,
    "likes": 0,
    "comments": 0,
    "saves": 0,
    "followers": 0,
    "shares": 0,
    "avgDuration": 9.0,
    "genre": "视频"
  },
  {
    "account": "18",
    "title": "羊肚菌不同时期长这样！各阶段特征识别指南",
    "publishDate": "2026-03-22",
    "exposure": 188,
    "views": 12,
    "ctr": 0.059,
    "likes": 0,
    "comments": 0,
    "saves": 0,
    "followers": 0,
    "shares": 0,
    "avgDuration": 3.0,
    "genre": "视频"
  },
  {
    "account": "二胎妈",
    "title": "来，泡发一箱海参～",
    "publishDate": "2026-03-22",
    "exposure": 116,
    "views": 11,
    "ctr": 0.019,
    "likes": 0,
    "comments": 0,
    "saves": 0,
    "followers": 0,
    "shares": 0,
    "avgDuration": 9.0,
    "genre": "视频"
  },
  {
    "account": "二胎妈",
    "title": "一吃就上瘾的海参，你吃过吗？",
    "publishDate": "2026-03-22",
    "exposure": 124,
    "views": 5,
    "ctr": 0.017,
    "likes": 0,
    "comments": 0,
    "saves": 0,
    "followers": 0,
    "shares": 0,
    "avgDuration": 2.0,
    "genre": "视频"
  },
  {
    "account": "二胎妈",
    "title": "奢华：深海软胶海参",
    "publishDate": "2026-03-22",
    "exposure": 153,
    "views": 5,
    "ctr": 0.033,
    "likes": 0,
    "comments": 0,
    "saves": 0,
    "followers": 0,
    "shares": 0,
    "avgDuration": 6.0,
    "genre": "视频"
  },
  {
    "account": "18",
    "title": "纹理清晰结构分明，长见识了",
    "publishDate": "2026-03-22",
    "exposure": 112,
    "views": 1,
    "ctr": 0.0,
    "likes": 1,
    "comments": 0,
    "saves": 0,
    "followers": 0,
    "shares": 0,
    "avgDuration": 20.0,
    "genre": "视频"
  },
  {
    "account": "18",
    "title": "真相全部藏在气温里，别贪图便宜",
    "publishDate": "2026-03-22",
    "exposure": 168,
    "views": 1,
    "ctr": 0.006,
    "likes": 0,
    "comments": 0,
    "saves": 0,
    "followers": 0,
    "shares": 0,
    "avgDuration": 15.0,
    "genre": "视频"
  },
  {
    "account": "二胎妈",
    "title": "分享一道早餐美食",
    "publishDate": "2026-03-22",
    "exposure": 138,
    "views": 0,
    "ctr": 0.0,
    "likes": 0,
    "comments": 0,
    "saves": 0,
    "followers": 0,
    "shares": 0,
    "avgDuration": 0.0,
    "genre": "视频"
  },
  {
    "account": "二胎妈",
    "title": "来自深海的馈赠，海参！",
    "publishDate": "2026-03-21",
    "exposure": 246,
    "views": 101,
    "ctr": 0.063,
    "likes": 0,
    "comments": 0,
    "saves": 1,
    "followers": 0,
    "shares": 0,
    "avgDuration": 22.0,
    "genre": "视频"
  },
  {
    "account": "二胎妈",
    "title": "这海水大刺参是真的吗",
    "publishDate": "2026-03-21",
    "exposure": 123,
    "views": 24,
    "ctr": 0.076,
    "likes": 0,
    "comments": 0,
    "saves": 0,
    "followers": 0,
    "shares": 0,
    "avgDuration": 6.0,
    "genre": "视频"
  },
  {
    "account": "18",
    "title": "深山采集的羊肚菌",
    "publishDate": "2026-03-21",
    "exposure": 252,
    "views": 17,
    "ctr": 0.068,
    "likes": 0,
    "comments": 0,
    "saves": 0,
    "followers": 0,
    "shares": 0,
    "avgDuration": 4.0,
    "genre": "视频"
  },
  {
    "account": "二胎妈",
    "title": "方便即食的海参",
    "publishDate": "2026-03-21",
    "exposure": 143,
    "views": 13,
    "ctr": 0.079,
    "likes": 0,
    "comments": 0,
    "saves": 0,
    "followers": 0,
    "shares": 0,
    "avgDuration": 12.0,
    "genre": "视频"
  },
  {
    "account": "18",
    "title": "怎么会有这么好吃的羊肚菌啊！",
    "publishDate": "2026-03-21",
    "exposure": 156,
    "views": 6,
    "ctr": 0.039,
    "likes": 0,
    "comments": 0,
    "saves": 0,
    "followers": 0,
    "shares": 0,
    "avgDuration": 8.0,
    "genre": "视频"
  },
  {
    "account": "18",
    "title": "小孩不爱吃饭，试试这个",
    "publishDate": "2026-03-21",
    "exposure": 143,
    "views": 6,
    "ctr": 0.007,
    "likes": 0,
    "comments": 0,
    "saves": 0,
    "followers": 0,
    "shares": 0,
    "avgDuration": 2.0,
    "genre": "视频"
  },
  {
    "account": "二胎妈",
    "title": "养生，要有好的食欲。",
    "publishDate": "2026-03-21",
    "exposure": 112,
    "views": 5,
    "ctr": 0.009,
    "likes": 1,
    "comments": 0,
    "saves": 0,
    "followers": 1,
    "shares": 0,
    "avgDuration": 4.0,
    "genre": "视频"
  },
  {
    "account": "18",
    "title": "晚饭的餐桌添加这个",
    "publishDate": "2026-03-21",
    "exposure": 132,
    "views": 2,
    "ctr": 0.015,
    "likes": 0,
    "comments": 0,
    "saves": 0,
    "followers": 0,
    "shares": 0,
    "avgDuration": 2.0,
    "genre": "视频"
  },
  {
    "account": "二胎妈",
    "title": "海参泡发天数还有讲究？",
    "publishDate": "2026-03-20",
    "exposure": 391,
    "views": 145,
    "ctr": 0.016,
    "likes": 0,
    "comments": 0,
    "saves": 0,
    "followers": 0,
    "shares": 0,
    "avgDuration": 3.0,
    "genre": "视频"
  },
  {
    "account": "二胎妈",
    "title": "来，看这碗菌菇汤！👀",
    "publishDate": "2026-03-20",
    "exposure": 422,
    "views": 45,
    "ctr": 0.053,
    "likes": 1,
    "comments": 0,
    "saves": 4,
    "followers": 1,
    "shares": 0,
    "avgDuration": 14.0,
    "genre": "视频"
  },
  {
    "account": "18",
    "title": "谁说羊肚菌只能熬羊肚菌汤？",
    "publishDate": "2026-03-20",
    "exposure": 248,
    "views": 32,
    "ctr": 0.112,
    "likes": 0,
    "comments": 0,
    "saves": 0,
    "followers": 0,
    "shares": 0,
    "avgDuration": 10.0,
    "genre": "视频"
  },
  {
    "account": "18",
    "title": "养生的超级英雄！🦸‍♀️",
    "publishDate": "2026-03-20",
    "exposure": 199,
    "views": 7,
    "ctr": 0.03,
    "likes": 0,
    "comments": 0,
    "saves": 0,
    "followers": 0,
    "shares": 0,
    "avgDuration": 6.0,
    "genre": "视频"
  },
  {
    "account": "二胎妈",
    "title": "🍅吃：鲜美的羊肚菌汤！",
    "publishDate": "2026-03-19",
    "exposure": 370,
    "views": 131,
    "ctr": 0.02,
    "likes": 1,
    "comments": 0,
    "saves": 0,
    "followers": 2,
    "shares": 0,
    "avgDuration": 16.0,
    "genre": "视频"
  },
  {
    "account": "二胎妈",
    "title": "免去了漫长等待！羊肚菌来了",
    "publishDate": "2026-03-19",
    "exposure": 391,
    "views": 65,
    "ctr": 0.057,
    "likes": 2,
    "comments": 0,
    "saves": 1,
    "followers": 1,
    "shares": 0,
    "avgDuration": 30.0,
    "genre": "视频"
  },
  {
    "account": "18",
    "title": "一盅一盏：再孤单的心也会被暖",
    "publishDate": "2026-03-19",
    "exposure": 444,
    "views": 54,
    "ctr": 0.013,
    "likes": 12,
    "comments": 0,
    "saves": 0,
    "followers": 0,
    "shares": 0,
    "avgDuration": 3.0,
    "genre": "视频"
  },
  {
    "account": "18",
    "title": "一朵灵芝经历了多少道工序",
    "publishDate": "2026-03-19",
    "exposure": 203,
    "views": 17,
    "ctr": 0.041,
    "likes": 1,
    "comments": 0,
    "saves": 0,
    "followers": 0,
    "shares": 0,
    "avgDuration": 6.0,
    "genre": "视频"
  },
  {
    "account": "18",
    "title": "🌧️雨后森林，谁在采摘灵芝？",
    "publishDate": "2026-03-19",
    "exposure": 220,
    "views": 15,
    "ctr": 0.038,
    "likes": 2,
    "comments": 0,
    "saves": 0,
    "followers": 0,
    "shares": 0,
    "avgDuration": 2.0,
    "genre": "视频"
  },
  {
    "account": "二胎妈",
    "title": "谁懂这汤的营养价值",
    "publishDate": "2026-03-19",
    "exposure": 226,
    "views": 9,
    "ctr": 0.023,
    "likes": 0,
    "comments": 0,
    "saves": 0,
    "followers": 0,
    "shares": 0,
    "avgDuration": 4.0,
    "genre": "视频"
  },
  {
    "account": "18",
    "title": "好喝的滋补汤｜不上火🔥",
    "publishDate": "2026-03-18",
    "exposure": 327,
    "views": 124,
    "ctr": 0.052,
    "likes": 0,
    "comments": 0,
    "saves": 1,
    "followers": 0,
    "shares": 0,
    "avgDuration": 3.0,
    "genre": "视频"
  },
  {
    "account": "二胎妈",
    "title": "这汤也太好喝了！鲜甜入味～",
    "publishDate": "2026-03-18",
    "exposure": 301,
    "views": 117,
    "ctr": 0.053,
    "likes": 1,
    "comments": 0,
    "saves": 3,
    "followers": 2,
    "shares": 0,
    "avgDuration": 5.0,
    "genre": "视频"
  },
  {
    "account": "18",
    "title": "见过这么大的灵芝吗",
    "publishDate": "2026-03-18",
    "exposure": 452,
    "views": 44,
    "ctr": 0.051,
    "likes": 0,
    "comments": 0,
    "saves": 0,
    "followers": 0,
    "shares": 0,
    "avgDuration": 4.0,
    "genre": "视频"
  },
  {
    "account": "18",
    "title": "万物皆可蒸！！！",
    "publishDate": "2026-03-18",
    "exposure": 232,
    "views": 16,
    "ctr": 0.018,
    "likes": 1,
    "comments": 0,
    "saves": 1,
    "followers": 1,
    "shares": 0,
    "avgDuration": 5.0,
    "genre": "视频"
  },
  {
    "account": "18",
    "title": "黑松露的滋补",
    "publishDate": "2026-03-18",
    "exposure": 142,
    "views": 12,
    "ctr": 0.058,
    "likes": 0,
    "comments": 0,
    "saves": 0,
    "followers": 0,
    "shares": 0,
    "avgDuration": 5.0,
    "genre": "视频"
  },
  {
    "account": "二胎妈",
    "title": "记录｜记忆深处的哪碗热汤",
    "publishDate": "2026-03-18",
    "exposure": 271,
    "views": 10,
    "ctr": 0.015,
    "likes": 0,
    "comments": 0,
    "saves": 0,
    "followers": 1,
    "shares": 0,
    "avgDuration": 4.0,
    "genre": "视频"
  },
  {
    "account": "18",
    "title": "惊呆了！还有这么大",
    "publishDate": "2026-03-18",
    "exposure": 276,
    "views": 6,
    "ctr": 0.018,
    "likes": 0,
    "comments": 0,
    "saves": 0,
    "followers": 0,
    "shares": 0,
    "avgDuration": 3.0,
    "genre": "视频"
  },
  {
    "account": "二胎妈",
    "title": "太白的灵芝我真不敢买",
    "publishDate": "2026-03-18",
    "exposure": 374,
    "views": 6,
    "ctr": 0.016,
    "likes": 0,
    "comments": 0,
    "saves": 1,
    "followers": 0,
    "shares": 0,
    "avgDuration": 35.0,
    "genre": "视频"
  },
  {
    "account": "二胎妈",
    "title": "买灵芝别再只看大小了",
    "publishDate": "2026-03-18",
    "exposure": 345,
    "views": 3,
    "ctr": 0.003,
    "likes": 0,
    "comments": 0,
    "saves": 0,
    "followers": 0,
    "shares": 0,
    "avgDuration": 6.0,
    "genre": "视频"
  },
  {
    "account": "18",
    "title": "老一辈留下的方子",
    "publishDate": "2026-03-18",
    "exposure": 53,
    "views": 2,
    "ctr": 0.019,
    "likes": 0,
    "comments": 0,
    "saves": 0,
    "followers": 0,
    "shares": 0,
    "avgDuration": 8.0,
    "genre": "视频"
  },
  {
    "account": "18",
    "title": "有谁知道这是什么野菇？",
    "publishDate": "2026-03-17",
    "exposure": 450,
    "views": 41,
    "ctr": 0.053,
    "likes": 2,
    "comments": 0,
    "saves": 0,
    "followers": 1,
    "shares": 0,
    "avgDuration": 16.0,
    "genre": "视频"
  },
  {
    "account": "18",
    "title": "没想到吧！制作竟然这么简单",
    "publishDate": "2026-03-17",
    "exposure": 223,
    "views": 40,
    "ctr": 0.052,
    "likes": 1,
    "comments": 0,
    "saves": 1,
    "followers": 1,
    "shares": 0,
    "avgDuration": 8.0,
    "genre": "视频"
  },
  {
    "account": "18",
    "title": "在森林里白伞菇🌿",
    "publishDate": "2026-03-17",
    "exposure": 496,
    "views": 39,
    "ctr": 0.05,
    "likes": 2,
    "comments": 0,
    "saves": 0,
    "followers": 1,
    "shares": 0,
    "avgDuration": 28.0,
    "genre": "视频"
  },
  {
    "account": "二胎妈",
    "title": "哇，这锅汤真的太好喝了！",
    "publishDate": "2026-03-17",
    "exposure": 485,
    "views": 36,
    "ctr": 0.055,
    "likes": 0,
    "comments": 0,
    "saves": 0,
    "followers": 0,
    "shares": 0,
    "avgDuration": 9.0,
    "genre": "视频"
  },
  {
    "account": "18",
    "title": "家人们谁懂啊！这颗松露是来报恩的吧！",
    "publishDate": "2026-03-17",
    "exposure": 249,
    "views": 33,
    "ctr": 0.105,
    "likes": 1,
    "comments": 0,
    "saves": 0,
    "followers": 0,
    "shares": 0,
    "avgDuration": 15.0,
    "genre": "视频"
  },
  {
    "account": "18",
    "title": "怎么会有这么好吃的黑松露！",
    "publishDate": "2026-03-17",
    "exposure": 163,
    "views": 18,
    "ctr": 0.089,
    "likes": 0,
    "comments": 0,
    "saves": 0,
    "followers": 1,
    "shares": 0,
    "avgDuration": 14.0,
    "genre": "视频"
  },
  {
    "account": "18",
    "title": "羊肚菌鸡蛋羹的美味",
    "publishDate": "2026-03-17",
    "exposure": 190,
    "views": 13,
    "ctr": 0.038,
    "likes": 0,
    "comments": 0,
    "saves": 0,
    "followers": 0,
    "shares": 0,
    "avgDuration": 3.0,
    "genre": "视频"
  },
  {
    "account": "二胎妈",
    "title": "这个灵芝纹理也太治愈了",
    "publishDate": "2026-03-17",
    "exposure": 159,
    "views": 11,
    "ctr": 0.027,
    "likes": 1,
    "comments": 0,
    "saves": 1,
    "followers": 0,
    "shares": 0,
    "avgDuration": 6.0,
    "genre": "视频"
  },
  {
    "account": "二胎妈",
    "title": "挖到隐藏的美味！🔥",
    "publishDate": "2026-03-17",
    "exposure": 436,
    "views": 9,
    "ctr": 0.023,
    "likes": 0,
    "comments": 0,
    "saves": 0,
    "followers": 0,
    "shares": 0,
    "avgDuration": 4.0,
    "genre": "视频"
  },
  {
    "account": "二胎妈",
    "title": "一口黑松露，瞬间点燃全家的味蕾",
    "publishDate": "2026-03-17",
    "exposure": 160,
    "views": 8,
    "ctr": 0.025,
    "likes": 0,
    "comments": 0,
    "saves": 0,
    "followers": 0,
    "shares": 0,
    "avgDuration": 33.0,
    "genre": "视频"
  },
  {
    "account": "二胎妈",
    "title": "绝了！这碗汤 你值得拥有！",
    "publishDate": "2026-03-17",
    "exposure": 145,
    "views": 6,
    "ctr": 0.014,
    "likes": 0,
    "comments": 0,
    "saves": 0,
    "followers": 0,
    "shares": 0,
    "avgDuration": 12.0,
    "genre": "视频"
  },
  {
    "account": "二胎妈",
    "title": "灵芝原来没想象中那么贵",
    "publishDate": "2026-03-17",
    "exposure": 146,
    "views": 3,
    "ctr": 0.007,
    "likes": 0,
    "comments": 0,
    "saves": 0,
    "followers": 0,
    "shares": 0,
    "avgDuration": 1.0,
    "genre": "视频"
  },
  {
    "account": "18",
    "title": "惊呆了！还有这么大的竹荪",
    "publishDate": "2026-03-16",
    "exposure": 1104,
    "views": 193,
    "ctr": 0.077,
    "likes": 4,
    "comments": 0,
    "saves": 1,
    "followers": 1,
    "shares": 1,
    "avgDuration": 18.0,
    "genre": "视频"
  },
  {
    "account": "18",
    "title": "竹荪季节刨刨刨",
    "publishDate": "2026-03-16",
    "exposure": 1276,
    "views": 159,
    "ctr": 0.1,
    "likes": 4,
    "comments": 0,
    "saves": 1,
    "followers": 2,
    "shares": 0,
    "avgDuration": 13.0,
    "genre": "视频"
  },
  {
    "account": "二胎妈",
    "title": "这竹荪吃起来，鲜香入味！",
    "publishDate": "2026-03-16",
    "exposure": 1311,
    "views": 139,
    "ctr": 0.049,
    "likes": 2,
    "comments": 0,
    "saves": 0,
    "followers": 0,
    "shares": 0,
    "avgDuration": 7.0,
    "genre": "视频"
  },
  {
    "account": "二胎妈",
    "title": "这碗蒸蛋，我先吃为敬！",
    "publishDate": "2026-03-16",
    "exposure": 1222,
    "views": 136,
    "ctr": 0.043,
    "likes": 1,
    "comments": 0,
    "saves": 4,
    "followers": 1,
    "shares": 0,
    "avgDuration": 5.0,
    "genre": "视频"
  },
  {
    "account": "二胎妈",
    "title": "美味的黑松露来了～",
    "publishDate": "2026-03-16",
    "exposure": 269,
    "views": 34,
    "ctr": 0.066,
    "likes": 0,
    "comments": 0,
    "saves": 0,
    "followers": 0,
    "shares": 0,
    "avgDuration": 9.0,
    "genre": "视频"
  },
  {
    "account": "18",
    "title": "羊肚菌：这口鲜，是舌尖的春天！",
    "publishDate": "2026-03-16",
    "exposure": 209,
    "views": 16,
    "ctr": 0.054,
    "likes": 0,
    "comments": 0,
    "saves": 0,
    "followers": 0,
    "shares": 0,
    "avgDuration": 6.0,
    "genre": "视频"
  },
  {
    "account": "18",
    "title": "谁懂啊，这菌蛋羹的含金量！",
    "publishDate": "2026-03-16",
    "exposure": 241,
    "views": 11,
    "ctr": 0.004,
    "likes": 1,
    "comments": 0,
    "saves": 0,
    "followers": 0,
    "shares": 0,
    "avgDuration": 4.0,
    "genre": "视频"
  },
  {
    "account": "18",
    "title": "是谁还没吃过松露？",
    "publishDate": "2026-03-16",
    "exposure": 361,
    "views": 9,
    "ctr": 0.028,
    "likes": 0,
    "comments": 0,
    "saves": 0,
    "followers": 0,
    "shares": 0,
    "avgDuration": 9.0,
    "genre": "视频"
  },
  {
    "account": "二胎妈",
    "title": "这几种简单美味做法",
    "publishDate": "2026-03-16",
    "exposure": 223,
    "views": 6,
    "ctr": 0.0,
    "likes": 0,
    "comments": 0,
    "saves": 0,
    "followers": 0,
    "shares": 0,
    "avgDuration": 8.0,
    "genre": "视频"
  },
  {
    "account": "18",
    "title": "好吃到舔盘的黑松露！",
    "publishDate": "2026-03-16",
    "exposure": 171,
    "views": 4,
    "ctr": 0.024,
    "likes": 0,
    "comments": 0,
    "saves": 0,
    "followers": 0,
    "shares": 0,
    "avgDuration": 2.0,
    "genre": "视频"
  },
  {
    "account": "二胎妈",
    "title": "雪裙仙子何时有动静？",
    "publishDate": "2026-03-14",
    "exposure": 1527,
    "views": 521,
    "ctr": 0.087,
    "likes": 6,
    "comments": 0,
    "saves": 6,
    "followers": 5,
    "shares": 0,
    "avgDuration": 7.0,
    "genre": "视频"
  },
  {
    "account": "二胎妈",
    "title": "从土里长出来的蛋",
    "publishDate": "2026-03-14",
    "exposure": 1551,
    "views": 362,
    "ctr": 0.105,
    "likes": 6,
    "comments": 0,
    "saves": 1,
    "followers": 1,
    "shares": 0,
    "avgDuration": 3.0,
    "genre": "视频"
  },
  {
    "account": "二胎妈",
    "title": "喝这汤真管用",
    "publishDate": "2026-03-14",
    "exposure": 972,
    "views": 272,
    "ctr": 0.06,
    "likes": 1,
    "comments": 0,
    "saves": 7,
    "followers": 0,
    "shares": 0,
    "avgDuration": 6.0,
    "genre": "视频"
  },
  {
    "account": "二胎妈",
    "title": "一碗热腾腾的羊肚菌汤，让你神经松绑",
    "publishDate": "2026-03-13",
    "exposure": 392,
    "views": 30,
    "ctr": 0.047,
    "likes": 0,
    "comments": 0,
    "saves": 0,
    "followers": 0,
    "shares": 0,
    "avgDuration": 5.0,
    "genre": "视频"
  },
  {
    "account": "18",
    "title": "真正的宝贝 羊肚菌",
    "publishDate": "2026-03-13",
    "exposure": 226,
    "views": 15,
    "ctr": 0.063,
    "likes": 0,
    "comments": 0,
    "saves": 1,
    "followers": 0,
    "shares": 0,
    "avgDuration": 8.0,
    "genre": "视频"
  },
  {
    "account": "二胎妈",
    "title": "野外的红蘑菇，这颗我先挖了！",
    "publishDate": "2026-03-12",
    "exposure": 2077,
    "views": 366,
    "ctr": 0.116,
    "likes": 6,
    "comments": 0,
    "saves": 0,
    "followers": 1,
    "shares": 0,
    "avgDuration": 4.0,
    "genre": "视频"
  },
  {
    "account": "二胎妈",
    "title": "谁说林下没人捡菌？",
    "publishDate": "2026-03-12",
    "exposure": 1357,
    "views": 194,
    "ctr": 0.056,
    "likes": 1,
    "comments": 1,
    "saves": 0,
    "followers": 0,
    "shares": 0,
    "avgDuration": 1.0,
    "genre": "视频"
  },
  {
    "account": "二胎妈",
    "title": "天，是红蘑菇！我捡到红蘑菇了！",
    "publishDate": "2026-03-12",
    "exposure": 1179,
    "views": 128,
    "ctr": 0.065,
    "likes": 1,
    "comments": 0,
    "saves": 1,
    "followers": 0,
    "shares": 0,
    "avgDuration": 2.0,
    "genre": "视频"
  },
  {
    "account": "二胎妈",
    "title": "慧眼识菌",
    "publishDate": "2026-03-12",
    "exposure": 1115,
    "views": 87,
    "ctr": 0.054,
    "likes": 1,
    "comments": 0,
    "saves": 0,
    "followers": 0,
    "shares": 0,
    "avgDuration": 3.0,
    "genre": "视频"
  },
  {
    "account": "二胎妈",
    "title": "终于找到这种小红菇了！👀",
    "publishDate": "2026-03-12",
    "exposure": 968,
    "views": 67,
    "ctr": 0.068,
    "likes": 3,
    "comments": 0,
    "saves": 0,
    "followers": 1,
    "shares": 1,
    "avgDuration": 1.0,
    "genre": "视频"
  },
  {
    "account": "18",
    "title": "是谁还没吃到这么新鲜的红菇",
    "publishDate": "2026-03-12",
    "exposure": 742,
    "views": 50,
    "ctr": 0.036,
    "likes": 1,
    "comments": 0,
    "saves": 0,
    "followers": 0,
    "shares": 0,
    "avgDuration": 4.0,
    "genre": "视频"
  },
  {
    "account": "18",
    "title": "我真的太爱这种红菇了！",
    "publishDate": "2026-03-12",
    "exposure": 418,
    "views": 46,
    "ctr": 0.061,
    "likes": 4,
    "comments": 0,
    "saves": 0,
    "followers": 0,
    "shares": 0,
    "avgDuration": 8.0,
    "genre": "视频"
  },
  {
    "account": "18",
    "title": "新鲜的红菌子来啦！",
    "publishDate": "2026-03-12",
    "exposure": 538,
    "views": 36,
    "ctr": 0.042,
    "likes": 1,
    "comments": 0,
    "saves": 0,
    "followers": 0,
    "shares": 0,
    "avgDuration": 14.0,
    "genre": "视频"
  },
  {
    "account": "18",
    "title": "草莓红菇你们挖到了吗？",
    "publishDate": "2026-03-12",
    "exposure": 30,
    "views": 4,
    "ctr": 0.103,
    "likes": 0,
    "comments": 0,
    "saves": 0,
    "followers": 0,
    "shares": 0,
    "avgDuration": 3.0,
    "genre": "视频"
  }
]
